{
  "type" : "FeatureCollection",
  "crs" : {
    "type" : "name",
    "properties" : {
      "name" : "EPSG:4326"
    }
  },
  "features" : [
    {
      "type" : "Feature",
      "id" : 0,
      "geometry" : {
        "type" : "Polygon",
        "coordinates" : [
          [
            [
              106.54994873366793,
              29.536207357125988
            ],
            [
              106.54878807466334,
              29.617375445580105
            ],
            [
              106.45589731175092,
              29.616326714702616
            ],
            [
              106.45713219378345,
              29.535162064399362
            ],
            [
              106.54994873366793,
              29.536207357125988
            ]
          ]
        ]
      },
      "properties" : {
        "FID" : 0,
        "SOURCE_ID" : 27,
        "Join_Count" : 31239,
        "GiZScore" : 26.856913943599999,
        "GiPValue" : 0,
        "Gi_Bin" : 3
      }
    },
    {
      "type" : "Feature",
      "id" : 1,
      "geometry" : {
        "type" : "Polygon",
        "coordinates" : [
          [
            [
              106.45713219378345,
              29.535162064399362
            ],
            [
              106.45589731175092,
              29.616326714702616
            ],
            [
              106.36301161522579,
              29.615212991892427
            ],
            [
              106.36432070327162,
              29.534051992732717
            ],
            [
              106.45713219378345,
              29.535162064399362
            ]
          ]
        ]
      },
      "properties" : {
        "FID" : 1,
        "SOURCE_ID" : 141,
        "Join_Count" : 4093,
        "GiZScore" : 3.4003317444399999,
        "GiPValue" : 0.00067304142857599997,
        "Gi_Bin" : 3
      }
    },
    {
      "type" : "Feature",
      "id" : 2,
      "geometry" : {
        "type" : "Polygon",
        "coordinates" : [
          [
            [
              106.55225582942592,
              29.37386808165601
            ],
            [
              106.55110464662224,
              29.455038235193594
            ],
            [
              106.45836202642657,
              29.453996375260644
            ],
            [
              106.45958682659457,
              29.372829649185974
            ],
            [
              106.55225582942592,
              29.37386808165601
            ]
          ]
        ]
      },
      "properties" : {
        "FID" : 2,
        "SOURCE_ID" : 215,
        "Join_Count" : 2686,
        "GiZScore" : 2.1828333453600002,
        "GiPValue" : 0.029048085075799999,
        "Gi_Bin" : 2
      }
    },
    {
      "type" : "Feature",
      "id" : 3,
      "geometry" : {
        "type" : "Polygon",
        "coordinates" : [
          [
            [
              106.54878807466334,
              29.617375445580105
            ],
            [
              106.54762265361428,
              29.698542498689914
            ],
            [
              106.45465736331423,
              29.697490324277826
            ],
            [
              106.45589731175092,
              29.616326714702616
            ],
            [
              106.54878807466334,
              29.617375445580105
            ]
          ]
        ]
      },
      "properties" : {
        "FID" : 3,
        "SOURCE_ID" : 225,
        "Join_Count" : 2852,
        "GiZScore" : 2.32815441842,
        "GiPValue" : 0.019903905563899999,
        "Gi_Bin" : 2
      }
    },
    {
      "type" : "Feature",
      "id" : 4,
      "geometry" : {
        "type" : "Polygon",
        "coordinates" : [
          [
            [
              106.64059272203204,
              29.699529455374993
            ],
            [
              106.63949737180815,
              29.780698706512716
            ],
            [
              106.54645245443164,
              29.779708514596521
            ],
            [
              106.54762265361428,
              29.698542498689914
            ],
            [
              106.64059272203204,
              29.699529455374993
            ]
          ]
        ]
      },
      "properties" : {
        "FID" : 4,
        "SOURCE_ID" : 285,
        "Join_Count" : 3160,
        "GiZScore" : 2.5912439034400001,
        "GiPValue" : 0.0095629688290500003,
        "Gi_Bin" : 3
      }
    },
    {
      "type" : "Feature",
      "id" : 5,
      "geometry" : {
        "type" : "Polygon",
        "coordinates" : [
          [
            [
              108.41190170103017,
              30.761271654951152
            ],
            [
              108.41224804301915,
              30.842448580968032
            ],
            [
              108.31816752987315,
              30.842713860048033
            ],
            [
              108.31790022402944,
              30.761536085310745
            ],
            [
              108.41190170103017,
              30.761271654951152
            ]
          ]
        ]
      },
      "properties" : {
        "FID" : 5,
        "SOURCE_ID" : 440,
        "Join_Count" : 5278,
        "GiZScore" : 4.4211133124400002,
        "GiPValue" : 9.8193661163600007e-006,
        "Gi_Bin" : 3
      }
    },
    {
      "type" : "Feature",
      "id" : 6,
      "geometry" : {
        "type" : "Polygon",
        "coordinates" : [
          [
            [
              107.11046845171589,
              29.135181818978001
            ],
            [
              107.10976795477674,
              29.216371084650913
            ],
            [
              107.01722167849616,
              29.215723301601965
            ],
            [
              107.01799497013802,
              29.134536178446112
            ],
            [
              107.11046845171589,
              29.135181818978001
            ]
          ]
        ]
      },
      "properties" : {
        "FID" : 6,
        "SOURCE_ID" : 449,
        "Join_Count" : 2268,
        "GiZScore" : 1.81992320234,
        "GiPValue" : 0.068770700960500003,
        "Gi_Bin" : 1
      }
    },
    {
      "type" : "Feature",
      "id" : 7,
      "geometry" : {
        "type" : "Polygon",
        "coordinates" : [
          [
            [
              106.45836202642657,
              29.453996375260644
            ],
            [
              106.45713219378345,
              29.535162064399362
            ],
            [
              106.36432070327162,
              29.534051992732717
            ],
            [
              106.36562443868939,
              29.452889949049226
            ],
            [
              106.45836202642657,
              29.453996375260644
            ]
          ]
        ]
      },
      "properties" : {
        "FID" : 7,
        "SOURCE_ID" : 503,
        "Join_Count" : 2813,
        "GiZScore" : 2.2929442345900002,
        "GiPValue" : 0.0218512156938,
        "Gi_Bin" : 2
      }
    },
    {
      "type" : "Feature",
      "id" : 8,
      "geometry" : {
        "type" : "Polygon",
        "coordinates" : [
          [
            [
              107.10405928935319,
              29.865849016871632
            ],
            [
              107.0109197786159,
              29.86518397348291
            ],
            [
              107.01171885273479,
              29.784004936441487
            ],
            [
              107.10478314219664,
              29.784667810446194
            ],
            [
              107.10405928935319,
              29.865849016871632
            ]
          ]
        ]
      },
      "properties" : {
        "FID" : 8,
        "SOURCE_ID" : 729,
        "Join_Count" : 2328,
        "GiZScore" : 1.8718074626400001,
        "GiPValue" : 0.0612332454641,
        "Gi_Bin" : 1
      }
    },
    {
      "type" : "Feature",
      "id" : 9,
      "geometry" : {
        "type" : "Polygon",
        "coordinates" : [
          [
            [
              106.27699130072335,
              29.208238129106878
            ],
            [
              106.27563053453686,
              29.289399454588647
            ],
            [
              106.18305074507759,
              29.288172058074043
            ],
            [
              106.18448447416188,
              29.207014784334842
            ],
            [
              106.27699130072335,
              29.208238129106878
            ]
          ]
        ]
      },
      "properties" : {
        "FID" : 9,
        "SOURCE_ID" : 758,
        "Join_Count" : 2439,
        "GiZScore" : 1.96777156418,
        "GiPValue" : 0.049094327399399999,
        "Gi_Bin" : 2
      }
    },
    {
      "type" : "Feature",
      "id" : 10,
      "geometry" : {
        "type" : "Polygon",
        "coordinates" : [
          [
            [
              106.55110464662224,
              29.455038235193594
            ],
            [
              106.54994873366793,
              29.536207357125988
            ],
            [
              106.45713219378345,
              29.535162064399362
            ],
            [
              106.45836202642657,
              29.453996375260644
            ],
            [
              106.55110464662224,
              29.455038235193594
            ]
          ]
        ]
      },
      "properties" : {
        "FID" : 10,
        "SOURCE_ID" : 781,
        "Join_Count" : 16980,
        "GiZScore" : 14.536745118900001,
        "GiPValue" : 0,
        "Gi_Bin" : 3
      }
    },
    {
      "type" : "Feature",
      "id" : 11,
      "geometry" : {
        "type" : "Polygon",
        "coordinates" : [
          [
            [
              106.45341233135755,
              29.778652891239371
            ],
            [
              106.45216219866327,
              29.859814413708673
            ],
            [
              106.3590520544364,
              29.858689703055298
            ],
            [
              106.36037730900398,
              29.777531848964227
            ],
            [
              106.45341233135755,
              29.778652891239371
            ]
          ]
        ]
      },
      "properties" : {
        "FID" : 11,
        "SOURCE_ID" : 844,
        "Join_Count" : 2289,
        "GiZScore" : 1.8381198159700001,
        "GiPValue" : 0.066044751820799996,
        "Gi_Bin" : 1
      }
    },
    {
      "type" : "Feature",
      "id" : 12,
      "geometry" : {
        "type" : "Polygon",
        "coordinates" : [
          [
            [
              108.8711148428294,
              29.54126381124032
            ],
            [
              108.7782708087815,
              29.541840016535442
            ],
            [
              108.77765021932417,
              29.460652395476785
            ],
            [
              108.86765826727233,
              29.460096115137418
            ],
            [
              108.86693577396687,
              29.462855838925865
            ],
            [
              108.86715601973458,
              29.463166023193477
            ],
            [
              108.86839745467887,
              29.463397666968838
            ],
            [
              108.86911828108386,
              29.463768526696185
            ],
            [
              108.86956876678522,
              29.46501865718535
            ],
            [
              108.86947864392431,
              29.465618291850717
            ],
            [
              108.86844738234089,
              29.467556074553279
            ],
            [
              108.86565399723425,
              29.471260687830522
            ],
            [
              108.86488307319534,
              29.471879362042959
            ],
            [
              108.86394195245919,
              29.472397838289691
            ],
            [
              108.86306090193915,
              29.472906403108073
            ],
            [
              108.86244015119206,
              29.473545279690931
            ],
            [
              108.86228996081309,
              29.47392491770086
            ],
            [
              108.86221982448535,
              29.475354248899521
            ],
            [
              108.8628003989193,
              29.47824390553188
            ],
            [
              108.86437202265081,
              29.484593567039553
            ],
            [
              108.86559332357308,
              29.48879359614762
            ],
            [
              108.86665451549356,
              29.490864252783055
            ],
            [
              108.86720515239591,
              29.491404807385997
            ],
            [
              108.86872694739078,
              29.491946719065872
            ],
            [
              108.8706916606105,
              29.491841578538768
            ],
            [
              108.8711148428294,
              29.54126381124032
            ]
          ]
        ]
      },
      "properties" : {
        "FID" : 12,
        "SOURCE_ID" : 851,
        "Join_Count" : 2179,
        "GiZScore" : 1.7431160986700001,
        "GiPValue" : 0.081313337085400006,
        "Gi_Bin" : 1
      }
    },
    {
      "type" : "Feature",
      "id" : 13,
      "geometry" : {
        "type" : "Polygon",
        "coordinates" : [
          [
            [
              106.64168359960436,
              29.61835917210988
            ],
            [
              106.64059272203204,
              29.699529455374993
            ],
            [
              106.54762265361428,
              29.698542498689914
            ],
            [
              106.54878807466334,
              29.617375445580105
            ],
            [
              106.64168359960436,
              29.61835917210988
            ]
          ]
        ]
      },
      "properties" : {
        "FID" : 13,
        "SOURCE_ID" : 853,
        "Join_Count" : 5449,
        "GiZScore" : 4.5701789935199999,
        "GiPValue" : 4.8730782374599996e-006,
        "Gi_Bin" : 3
      }
    },
    {
      "type" : "Feature",
      "id" : 14,
      "geometry" : {
        "type" : "Polygon",
        "coordinates" : [
          [
            [
              106.54878807466334,
              29.617375445580105
            ],
            [
              106.54994873366793,
              29.536207357125988
            ],
            [
              106.64277001958702,
              29.537187858551249
            ],
            [
              106.64168359960436,
              29.61835917210988
            ],
            [
              106.54878807466334,
              29.617375445580105
            ]
          ]
        ]
      },
      "properties" : {
        "FID" : 14,
        "SOURCE_ID" : 855,
        "Join_Count" : 10236,
        "GiZScore" : 8.7093683900799999,
        "GiPValue" : 0,
        "Gi_Bin" : 3
      }
    },
    {
      "type" : "Feature",
      "id" : 15,
      "geometry" : {
        "type" : "Polygon",
        "coordinates" : [
          [
            [
              106.27151456537011,
              29.532877155252006
            ],
            [
              106.2701312893456,
              29.614034290332473
            ],
            [
              106.1772566382608,
              29.612790623973243
            ],
            [
              106.17871408321011,
              29.531637565847429
            ],
            [
              106.27151456537011,
              29.532877155252006
            ]
          ]
        ]
      },
      "properties" : {
        "FID" : 15,
        "SOURCE_ID" : 919,
        "Join_Count" : 2075,
        "GiZScore" : 1.6532958261799999,
        "GiPValue" : 0.098270672032999995,
        "Gi_Bin" : 1
      }
    },
    {
      "type" : "Feature",
      "id" : 16,
      "geometry" : {
        "type" : "Polygon",
        "coordinates" : [
          [
            [
              106.64385199695292,
              29.456015516540187
            ],
            [
              106.64277001958702,
              29.537187858551249
            ],
            [
              106.54994873366793,
              29.536207357125988
            ],
            [
              106.55110464662224,
              29.455038235193594
            ],
            [
              106.64385199695292,
              29.456015516540187
            ]
          ]
        ]
      },
      "properties" : {
        "FID" : 16,
        "SOURCE_ID" : 953,
        "Join_Count" : 7589,
        "GiZScore" : 6.4204986745200001,
        "GiPValue" : 1.3582865334e-010,
        "Gi_Bin" : 3
      }
    }
  ]
}