{
  "type" : "FeatureCollection",
  "crs" : {
    "type" : "name",
    "properties" : {
      "name" : "EPSG:4326"
    }
  },
  "features" : [
    {
      "type" : "Feature",
      "id" : 0,
      "geometry" : {
        "type" : "Polygon",
        "coordinates" : [
          [
            [
              108.41190170103017,
              30.761271654951138
            ],
            [
              108.41213243951771,
              30.815389719110229
            ],
            [
              108.349429821193,
              30.815573967828787
            ],
            [
              108.34923418580514,
              30.761455510374077
            ],
            [
              108.41190170103017,
              30.761271654951138
            ]
          ]
        ]
      },
      "properties" : {
        "FID" : 0,
        "SOURCE_ID" : 69,
        "Join_Count" : 9691,
        "GiZScore" : 6.7780464128100002,
        "GiPValue" : 1.2181172225500001e-011,
        "Gi_Bin" : 3
      }
    },
    {
      "type" : "Feature",
      "id" : 1,
      "geometry" : {
        "type" : "Polygon",
        "coordinates" : [
          [
            [
              106.68033514065223,
              29.023385028285844
            ],
            [
              106.6796460018405,
              29.077504350101261
            ],
            [
              106.61804031930326,
              29.076884002848459
            ],
            [
              106.61876158790065,
              29.022766053209786
            ],
            [
              106.68033514065223,
              29.023385028285844
            ]
          ]
        ]
      },
      "properties" : {
        "FID" : 1,
        "SOURCE_ID" : 105,
        "Join_Count" : 6355,
        "GiZScore" : 4.3710002855300001,
        "GiPValue" : 1.23678631171e-005,
        "Gi_Bin" : 3
      }
    },
    {
      "type" : "Feature",
      "id" : 2,
      "geometry" : {
        "type" : "Polygon",
        "coordinates" : [
          [
            [
              106.67193958087786,
              29.672786956289862
            ],
            [
              106.67122744116863,
              29.726900821337939
            ],
            [
              106.60922926234858,
              29.726263897412963
            ],
            [
              106.60997460373382,
              29.672151421652991
            ],
            [
              106.67193958087786,
              29.672786956289862
            ]
          ]
        ]
      },
      "properties" : {
        "FID" : 2,
        "SOURCE_ID" : 112,
        "Join_Count" : 5194,
        "GiZScore" : 3.5345198505400002,
        "GiPValue" : 0.00040851674925399998,
        "Gi_Bin" : 3
      }
    },
    {
      "type" : "Feature",
      "id" : 3,
      "geometry" : {
        "type" : "Polygon",
        "coordinates" : [
          [
            [
              108.22052054000703,
              29.246217026006043
            ],
            [
              108.22063676372538,
              29.300348565342958
            ],
            [
              108.15888065996975,
              29.300436302564261
            ],
            [
              108.15879696680554,
              29.246304570049482
            ],
            [
              108.22052054000703,
              29.246217026006043
            ]
          ]
        ]
      },
      "properties" : {
        "FID" : 3,
        "SOURCE_ID" : 143,
        "Join_Count" : 2950,
        "GiZScore" : 1.9155093347400001,
        "GiPValue" : 0.055427579837499998,
        "Gi_Bin" : 1
      }
    },
    {
      "type" : "Feature",
      "id" : 4,
      "geometry" : {
        "type" : "Polygon",
        "coordinates" : [
          [
            [
              108.41213243951771,
              30.815389719110229
            ],
            [
              108.41236380293537,
              30.86950732926778
            ],
            [
              108.34962598644124,
              30.869691971713486
            ],
            [
              108.349429821193,
              30.815573967828787
            ],
            [
              108.41213243951771,
              30.815389719110229
            ]
          ]
        ]
      },
      "properties" : {
        "FID" : 4,
        "SOURCE_ID" : 146,
        "Join_Count" : 7150,
        "GiZScore" : 4.9454013552899996,
        "GiPValue" : 7.5987141992799998e-007,
        "Gi_Bin" : 3
      }
    },
    {
      "type" : "Feature",
      "id" : 5,
      "geometry" : {
        "type" : "Polygon",
        "coordinates" : [
          [
            [
              106.48927568892394,
              29.45435083655935
            ],
            [
              106.4884727748623,
              29.50846218971316
            ],
            [
              106.42661318195972,
              29.507744520538871
            ],
            [
              106.42744892309206,
              29.453634739924698
            ],
            [
              106.48927568892394,
              29.45435083655935
            ]
          ]
        ]
      },
      "properties" : {
        "FID" : 5,
        "SOURCE_ID" : 148,
        "Join_Count" : 13452,
        "GiZScore" : 9.4938099580300008,
        "GiPValue" : 0,
        "Gi_Bin" : 3
      }
    },
    {
      "type" : "Feature",
      "id" : 6,
      "geometry" : {
        "type" : "Polygon",
        "coordinates" : [
          [
            [
              107.11046845171589,
              29.135181818977994
            ],
            [
              107.11000177388104,
              29.189308107256455
            ],
            [
              107.04832011640661,
              29.188883831007416
            ],
            [
              107.04881912601866,
              29.134758479042123
            ],
            [
              107.11046845171589,
              29.135181818977994
            ]
          ]
        ]
      },
      "properties" : {
        "FID" : 6,
        "SOURCE_ID" : 156,
        "Join_Count" : 8378,
        "GiZScore" : 5.8299184316600003,
        "GiPValue" : 5.5454475867499999e-009,
        "Gi_Bin" : 3
      }
    },
    {
      "type" : "Feature",
      "id" : 7,
      "geometry" : {
        "type" : "Polygon",
        "coordinates" : [
          [
            [
              106.4224000753641,
              29.77828647860893
            ],
            [
              106.42155053768448,
              29.832393477290267
            ],
            [
              106.35949440787373,
              29.831637201838554
            ],
            [
              106.36037730900398,
              29.777531848964241
            ],
            [
              106.4224000753641,
              29.77828647860893
            ]
          ]
        ]
      },
      "properties" : {
        "FID" : 7,
        "SOURCE_ID" : 196,
        "Join_Count" : 2699,
        "GiZScore" : 1.73474330983,
        "GiPValue" : 0.082786281387599997,
        "Gi_Bin" : 1
      }
    },
    {
      "type" : "Feature",
      "id" : 8,
      "geometry" : {
        "type" : "Polygon",
        "coordinates" : [
          [
            [
              107.78834234007799,
              29.300363095991329
            ],
            [
              107.7882305404039,
              29.354494227891205
            ],
            [
              107.7264420843151,
              29.35438184191727
            ],
            [
              107.72658650315518,
              29.300250957176207
            ],
            [
              107.78834234007799,
              29.300363095991329
            ]
          ]
        ]
      },
      "properties" : {
        "FID" : 8,
        "SOURCE_ID" : 235,
        "Join_Count" : 3560,
        "GiZScore" : 2.3551270091099998,
        "GiPValue" : 0.0185163756633,
        "Gi_Bin" : 2
      }
    },
    {
      "type" : "Feature",
      "id" : 9,
      "geometry" : {
        "type" : "Polygon",
        "coordinates" : [
          [
            [
              109.48039851575983,
              30.969918799755817
            ],
            [
              109.48123459356185,
              31.024018382235703
            ],
            [
              109.41841437703732,
              31.024724100381651
            ],
            [
              109.41761372829522,
              30.970623017916168
            ],
            [
              109.48039851575983,
              30.969918799755817
            ]
          ]
        ]
      },
      "properties" : {
        "FID" : 9,
        "SOURCE_ID" : 324,
        "Join_Count" : 4045,
        "GiZScore" : 2.70511529351,
        "GiPValue" : 0.0068280686344900001,
        "Gi_Bin" : 3
      }
    },
    {
      "type" : "Feature",
      "id" : 10,
      "geometry" : {
        "type" : "Polygon",
        "coordinates" : [
          [
            [
              106.29467688948466,
              29.993159907761402
            ],
            [
              106.29375059825797,
              30.047261671462952
            ],
            [
              106.23156505578069,
              30.046440026166064
            ],
            [
              106.23252506428621,
              29.992340042505646
            ],
            [
              106.29467688948466,
              29.993159907761402
            ]
          ]
        ]
      },
      "properties" : {
        "FID" : 10,
        "SOURCE_ID" : 366,
        "Join_Count" : 6275,
        "GiZScore" : 4.31367329404,
        "GiPValue" : 1.6056417238800002e-005,
        "Gi_Bin" : 3
      }
    },
    {
      "type" : "Feature",
      "id" : 11,
      "geometry" : {
        "type" : "Polygon",
        "coordinates" : [
          [
            [
              108.03571205478944,
              30.274825302371912
            ],
            [
              108.0357316761508,
              30.328948806388983
            ],
            [
              107.97333987273976,
              30.328950969970656
            ],
            [
              107.97335451263655,
              30.274827461290847
            ],
            [
              108.03571205478944,
              30.274825302371912
            ]
          ]
        ]
      },
      "properties" : {
        "FID" : 11,
        "SOURCE_ID" : 439,
        "Join_Count" : 3227,
        "GiZScore" : 2.1152464531100001,
        "GiPValue" : 0.0344089476342,
        "Gi_Bin" : 2
      }
    },
    {
      "type" : "Feature",
      "id" : 12,
      "geometry" : {
        "type" : "Polygon",
        "coordinates" : [
          [
            [
              107.10478314219664,
              29.784667810446209
            ],
            [
              107.10430090247449,
              29.838788727447113
            ],
            [
              107.04222428597951,
              29.838353139625404
            ],
            [
              107.04273993538868,
              29.784233170672429
            ],
            [
              107.10478314219664,
              29.784667810446209
            ]
          ]
        ]
      },
      "properties" : {
        "FID" : 12,
        "SOURCE_ID" : 530,
        "Join_Count" : 4677,
        "GiZScore" : 3.16157564881,
        "GiPValue" : 0.0015691805359800001,
        "Gi_Bin" : 3
      }
    },
    {
      "type" : "Feature",
      "id" : 13,
      "geometry" : {
        "type" : "Polygon",
        "coordinates" : [
          [
            [
              109.0149560363941,
              28.430583703859682
            ],
            [
              109.0154732393876,
              28.484713666585435
            ],
            [
              108.95420657679109,
              28.485157457982776
            ],
            [
              108.95372056636278,
              28.431026500273568
            ],
            [
              109.0149560363941,
              28.430583703859682
            ]
          ]
        ]
      },
      "properties" : {
        "FID" : 13,
        "SOURCE_ID" : 564,
        "Join_Count" : 6143,
        "GiZScore" : 4.2180282659500001,
        "GiPValue" : 2.46447930875e-005,
        "Gi_Bin" : 3
      }
    },
    {
      "type" : "Feature",
      "id" : 14,
      "geometry" : {
        "type" : "Polygon",
        "coordinates" : [
          [
            [
              107.34943939210825,
              30.327335821508921
            ],
            [
              107.3490812089826,
              30.381455397393065
            ],
            [
              107.32763504992613,
              30.381346797350986
            ],
            [
              107.32750208175571,
              30.381119985099293
            ],
            [
              107.32670387408456,
              30.379981409214739
            ],
            [
              107.32583582056674,
              30.378782949273731
            ],
            [
              107.32490789378431,
              30.377584579264983
            ],
            [
              107.32384028250311,
              30.376216452327469
            ],
            [
              107.3229023687494,
              30.375128075700157
            ],
            [
              107.32131582346653,
              30.373820714154704
            ],
            [
              107.32044778613647,
              30.372672244828259
            ],
            [
              107.31925045484468,
              30.371364299622773
            ],
            [
              107.31813291949869,
              30.37033618027057
            ],
            [
              107.31769389295887,
              30.369906923965406
            ],
            [
              107.31699544798158,
              30.369198112502954
            ],
            [
              107.31566837329683,
              30.368060328021773
            ],
            [
              107.31427145906066,
              30.3668626603835
            ],
            [
              107.31261508681689,
              30.365665382151686
            ],
            [
              107.31141774383389,
              30.364637381510018
            ],
            [
              107.31098868088297,
              30.364358080860754
            ],
            [
              107.30996093115209,
              30.36366975865247
            ],
            [
              107.30952187133738,
              30.36350045048545
            ],
            [
              107.30844417595802,
              30.363102144348542
            ],
            [
              107.30724675113669,
              30.362594040882364
            ],
            [
              107.30584981711542,
              30.361686315571035
            ],
            [
              107.30474225704961,
              30.360938124594838
            ],
            [
              107.30439302421877,
              30.360718691814206
            ],
            [
              107.30306601158726,
              30.359520919854617
            ],
            [
              107.30173900615029,
              30.358323147895028
            ],
            [
              107.29975304047048,
              30.35718603071081
            ],
            [
              107.29855401755394,
              30.356036341004359
            ],
            [
              107.29776462413817,
              30.355416511163135
            ],
            [
              107.29616586516259,
              30.354046870666604
            ],
            [
              107.29496683415215,
              30.352787181283414
            ],
            [
              107.29397765814248,
              30.351587465888894
            ],
            [
              107.29337819075096,
              30.350667675273026
            ],
            [
              107.29276873638815,
              30.349697892243956
            ],
            [
              107.2923091702321,
              30.348838081012676
            ],
            [
              107.29183956494406,
              30.348218222393083
            ],
            [
              107.29084034710438,
              30.347188467174064
            ],
            [
              107.29011093487179,
              30.346328664935996
            ],
            [
              107.28918169867649,
              30.345128934252951
            ],
            [
              107.28805260524361,
              30.343759242495079
            ],
            [
              107.2869402554653,
              30.342590643952327
            ],
            [
              107.28705314782724,
              30.327010647119369
            ],
            [
              107.34943939210825,
              30.327335821508921
            ]
          ]
        ]
      },
      "properties" : {
        "FID" : 14,
        "SOURCE_ID" : 586,
        "Join_Count" : 5347,
        "GiZScore" : 3.6441865208199999,
        "GiPValue" : 0.000268238847266,
        "Gi_Bin" : 3
      }
    },
    {
      "type" : "Feature",
      "id" : 15,
      "geometry" : {
        "type" : "Polygon",
        "coordinates" : [
          [
            [
              105.85500435138054,
              30.20315436077718
            ],
            [
              105.79273746801969,
              30.202120478828292
            ],
            [
              105.79394310847645,
              30.148036203053916
            ],
            [
              105.85617604516862,
              30.149067852832687
            ],
            [
              105.85500435138054,
              30.20315436077718
            ]
          ]
        ]
      },
      "properties" : {
        "FID" : 15,
        "SOURCE_ID" : 634,
        "Join_Count" : 8021,
        "GiZScore" : 5.5722912083600002,
        "GiPValue" : 2.5141071295200001e-008,
        "Gi_Bin" : 3
      }
    },
    {
      "type" : "Feature",
      "id" : 16,
      "geometry" : {
        "type" : "Polygon",
        "coordinates" : [
          [
            [
              108.4745685927803,
              30.76105752629795
            ],
            [
              108.47483443291324,
              30.815175132404082
            ],
            [
              108.41213243951771,
              30.815389719110229
            ],
            [
              108.41190170103017,
              30.761271654951138
            ],
            [
              108.4745685927803,
              30.76105752629795
            ]
          ]
        ]
      },
      "properties" : {
        "FID" : 16,
        "SOURCE_ID" : 648,
        "Join_Count" : 3526,
        "GiZScore" : 2.3319438030800002,
        "GiPValue" : 0.019703647712100002,
        "Gi_Bin" : 2
      }
    },
    {
      "type" : "Feature",
      "id" : 17,
      "geometry" : {
        "type" : "Polygon",
        "coordinates" : [
          [
            [
              105.93511177611195,
              29.338682023624244
            ],
            [
              105.93401960666588,
              29.392777910800145
            ],
            [
              105.87224927994458,
              29.391805856159365
            ],
            [
              105.87337404479715,
              29.337712103562808
            ],
            [
              105.93511177611195,
              29.338682023624244
            ]
          ]
        ]
      },
      "properties" : {
        "FID" : 17,
        "SOURCE_ID" : 680,
        "Join_Count" : 13974,
        "GiZScore" : 9.8656212019700007,
        "GiPValue" : 0,
        "Gi_Bin" : 3
      }
    },
    {
      "type" : "Feature",
      "id" : 18,
      "geometry" : {
        "type" : "Polygon",
        "coordinates" : [
          [
            [
              107.72512439563384,
              29.841539936313872
            ],
            [
              107.72497597830684,
              29.89566639680827
            ],
            [
              107.66285678502349,
              29.895522276654717
            ],
            [
              107.66303872370787,
              29.841396129500577
            ],
            [
              107.72512439563384,
              29.841539936313872
            ]
          ]
        ]
      },
      "properties" : {
        "FID" : 18,
        "SOURCE_ID" : 698,
        "Join_Count" : 3984,
        "GiZScore" : 2.6615155292899999,
        "GiPValue" : 0.0077789752504999997,
        "Gi_Bin" : 3
      }
    },
    {
      "type" : "Feature",
      "id" : 19,
      "geometry" : {
        "type" : "Polygon",
        "coordinates" : [
          [
            [
              106.61219846120389,
              29.509811241440993
            ],
            [
              106.6114591986107,
              29.563925093120158
            ],
            [
              106.54956237545987,
              29.563263501533907
            ],
            [
              106.55033456453785,
              29.509151097887084
            ],
            [
              106.61219846120389,
              29.509811241440993
            ]
          ]
        ]
      },
      "properties" : {
        "FID" : 19,
        "SOURCE_ID" : 1029,
        "Join_Count" : 22097,
        "GiZScore" : 15.728232244000001,
        "GiPValue" : 0,
        "Gi_Bin" : 3
      }
    },
    {
      "type" : "Feature",
      "id" : 20,
      "geometry" : {
        "type" : "Polygon",
        "coordinates" : [
          [
            [
              106.11129488353824,
              29.82832081669876
            ],
            [
              106.11027581280933,
              29.882418477796179
            ],
            [
              106.04819920989551,
              29.881514617931991
            ],
            [
              106.04925170570228,
              29.827418921445819
            ],
            [
              106.11129488353824,
              29.82832081669876
            ]
          ]
        ]
      },
      "properties" : {
        "FID" : 20,
        "SOURCE_ID" : 1082,
        "Join_Count" : 6256,
        "GiZScore" : 4.2997333216799998,
        "GiPValue" : 1.71003757335e-005,
        "Gi_Bin" : 3
      }
    },
    {
      "type" : "Feature",
      "id" : 21,
      "geometry" : {
        "type" : "Polygon",
        "coordinates" : [
          [
            [
              106.48442515409856,
              29.779012035094791
            ],
            [
              106.4836089850988,
              29.833120616199146
            ],
            [
              106.42155053768448,
              29.832393477290267
            ],
            [
              106.4224000753641,
              29.77828647860893
            ],
            [
              106.48442515409856,
              29.779012035094791
            ]
          ]
        ]
      },
      "properties" : {
        "FID" : 21,
        "SOURCE_ID" : 1125,
        "Join_Count" : 3000,
        "GiZScore" : 1.9518314136499999,
        "GiPValue" : 0.050958223362899999,
        "Gi_Bin" : 1
      }
    },
    {
      "type" : "Feature",
      "id" : 22,
      "geometry" : {
        "type" : "Polygon",
        "coordinates" : [
          [
            [
              106.29560066415463,
              29.939057673212258
            ],
            [
              106.29467688948466,
              29.993159907761402
            ],
            [
              106.23252506428621,
              29.992340042505646
            ],
            [
              106.23348246469983,
              29.938239586113109
            ],
            [
              106.29560066415463,
              29.939057673212258
            ]
          ]
        ]
      },
      "properties" : {
        "FID" : 22,
        "SOURCE_ID" : 1132,
        "Join_Count" : 4583,
        "GiZScore" : 3.0936632064,
        "GiPValue" : 0.00197701779212,
        "Gi_Bin" : 3
      }
    },
    {
      "type" : "Feature",
      "id" : 23,
      "geometry" : {
        "type" : "Polygon",
        "coordinates" : [
          [
            [
              109.85915643958997,
              31.073231281778313
            ],
            [
              109.9219943058836,
              31.072309806119641
            ],
            [
              109.92308409349415,
              31.126396095215167
            ],
            [
              109.86021064850263,
              31.127319529386522
            ],
            [
              109.85915643958997,
              31.073231281778313
            ]
          ]
        ]
      },
      "properties" : {
        "FID" : 23,
        "SOURCE_ID" : 1134,
        "Join_Count" : 6039,
        "GiZScore" : 4.1429942715000001,
        "GiPValue" : 3.4280051123000002e-005,
        "Gi_Bin" : 3
      }
    },
    {
      "type" : "Feature",
      "id" : 24,
      "geometry" : {
        "type" : "Polygon",
        "coordinates" : [
          [
            [
              106.48766766402447,
              29.562573082251937
            ],
            [
              106.48686035148448,
              29.616683513616518
            ],
            [
              106.42493483495007,
              29.61596269445652
            ],
            [
              106.42577515428805,
              29.561853838904334
            ],
            [
              106.48766766402447,
              29.562573082251937
            ]
          ]
        ]
      },
      "properties" : {
        "FID" : 24,
        "SOURCE_ID" : 1151,
        "Join_Count" : 10508,
        "GiZScore" : 7.3730353186000004,
        "GiPValue" : 0,
        "Gi_Bin" : 3
      }
    },
    {
      "type" : "Feature",
      "id" : 25,
      "geometry" : {
        "type" : "Polygon",
        "coordinates" : [
          [
            [
              106.30738329404052,
              29.235686035973398
            ],
            [
              106.30649172345281,
              29.289794339613881
            ],
            [
              106.24476996776092,
              29.288997445637776
            ],
            [
              106.2456939926892,
              29.234890896212022
            ],
            [
              106.30738329404052,
              29.235686035973398
            ]
          ]
        ]
      },
      "properties" : {
        "FID" : 25,
        "SOURCE_ID" : 1155,
        "Join_Count" : 8835,
        "GiZScore" : 6.1598374011399999,
        "GiPValue" : 7.2819673907999999e-010,
        "Gi_Bin" : 3
      }
    },
    {
      "type" : "Feature",
      "id" : 26,
      "geometry" : {
        "type" : "Polygon",
        "coordinates" : [
          [
            [
              108.7264500146234,
              30.922242311740046
            ],
            [
              108.72685955061507,
              30.976356065047774
            ],
            [
              108.66405515557241,
              30.976694146465903
            ],
            [
              108.66368099895993,
              30.92257967374589
            ],
            [
              108.7264500146234,
              30.922242311740046
            ]
          ]
        ]
      },
      "properties" : {
        "FID" : 26,
        "SOURCE_ID" : 1290,
        "Join_Count" : 7113,
        "GiZScore" : 4.9175623970500002,
        "GiPValue" : 8.76285298891e-007,
        "Gi_Bin" : 3
      }
    },
    {
      "type" : "Feature",
      "id" : 27,
      "geometry" : {
        "type" : "Polygon",
        "coordinates" : [
          [
            [
              105.74271926621104,
              29.660215194328281
            ],
            [
              105.7415096745021,
              29.714301580524108
            ],
            [
              105.67955153093726,
              29.713229782032951
            ],
            [
              105.68079423432903,
              29.659145733110979
            ],
            [
              105.74271926621104,
              29.660215194328281
            ]
          ]
        ]
      },
      "properties" : {
        "FID" : 27,
        "SOURCE_ID" : 1325,
        "Join_Count" : 6173,
        "GiZScore" : 4.2396343937600003,
        "GiPValue" : 2.2388412430200001e-005,
        "Gi_Bin" : 3
      }
    },
    {
      "type" : "Feature",
      "id" : 28,
      "geometry" : {
        "type" : "Polygon",
        "coordinates" : [
          [
            [
              108.15990302738628,
              29.949982687835398
            ],
            [
              108.15998974464947,
              30.004108671251466
            ],
            [
              108.09780231641354,
              30.004169561343765
            ],
            [
              108.09774930566073,
              29.95004344583722
            ],
            [
              108.15990302738628,
              29.949982687835398
            ]
          ]
        ]
      },
      "properties" : {
        "FID" : 28,
        "SOURCE_ID" : 1331,
        "Join_Count" : 4252,
        "GiZScore" : 2.8542030924100001,
        "GiPValue" : 0.0043144939842599999,
        "Gi_Bin" : 3
      }
    },
    {
      "type" : "Feature",
      "id" : 29,
      "geometry" : {
        "type" : "Polygon",
        "coordinates" : [
          [
            [
              105.808157812693,
              29.498986877876856
            ],
            [
              105.80699093177482,
              29.553076988534645
            ],
            [
              105.74512857349532,
              29.552040963277605
            ],
            [
              105.74632830381965,
              29.497953119695463
            ],
            [
              105.808157812693,
              29.498986877876856
            ]
          ]
        ]
      },
      "properties" : {
        "FID" : 29,
        "SOURCE_ID" : 1360,
        "Join_Count" : 2589,
        "GiZScore" : 1.6554372255300001,
        "GiPValue" : 0.097835840152999995,
        "Gi_Bin" : 1
      }
    },
    {
      "type" : "Feature",
      "id" : 30,
      "geometry" : {
        "type" : "Polygon",
        "coordinates" : [
          [
            [
              107.78721047146944,
              29.841654558307713
            ],
            [
              107.78709557641555,
              29.895781268552284
            ],
            [
              107.72497597830684,
              29.89566639680827
            ],
            [
              107.72512439563384,
              29.841539936313872
            ],
            [
              107.78721047146944,
              29.841654558307713
            ]
          ]
        ]
      },
      "properties" : {
        "FID" : 30,
        "SOURCE_ID" : 1479,
        "Join_Count" : 5057,
        "GiZScore" : 3.4352553912800001,
        "GiPValue" : 0.00059199563302000002,
        "Gi_Bin" : 3
      }
    },
    {
      "type" : "Feature",
      "id" : 31,
      "geometry" : {
        "type" : "Polygon",
        "coordinates" : [
          [
            [
              105.62519966039181,
              29.387631782411603
            ],
            [
              105.62394114841885,
              29.441715881317048
            ],
            [
              105.5621544625961,
              29.440598475766592
            ],
            [
              105.56344562276472,
              29.386516827524382
            ],
            [
              105.62519966039181,
              29.387631782411603
            ]
          ]
        ]
      },
      "properties" : {
        "FID" : 31,
        "SOURCE_ID" : 1604,
        "Join_Count" : 9419,
        "GiZScore" : 6.58057941686,
        "GiPValue" : 4.68618443125e-011,
        "Gi_Bin" : 3
      }
    },
    {
      "type" : "Feature",
      "id" : 32,
      "geometry" : {
        "type" : "Polygon",
        "coordinates" : [
          [
            [
              108.83994351762418,
              29.514401069769448
            ],
            [
              108.84039105487189,
              29.568524989801894
            ],
            [
              108.77847823784964,
              29.568902333729834
            ],
            [
              108.77806366288245,
              29.514777587719106
            ],
            [
              108.83994351762418,
              29.514401069769448
            ]
          ]
        ]
      },
      "properties" : {
        "FID" : 32,
        "SOURCE_ID" : 1624,
        "Join_Count" : 4403,
        "GiZScore" : 2.9636108870900002,
        "GiPValue" : 0.0030405249216799999,
        "Gi_Bin" : 3
      }
    },
    {
      "type" : "Feature",
      "id" : 33,
      "geometry" : {
        "type" : "Polygon",
        "coordinates" : [
          [
            [
              107.41564477985838,
              29.678153617938928
            ],
            [
              107.4153313431591,
              29.732279215276893
            ],
            [
              107.35331581302269,
              29.731990759344676
            ],
            [
              107.35366249043368,
              29.677865791268225
            ],
            [
              107.41564477985838,
              29.678153617938928
            ]
          ]
        ]
      },
      "properties" : {
        "FID" : 33,
        "SOURCE_ID" : 1763,
        "Join_Count" : 11249,
        "GiZScore" : 7.9003307772099998,
        "GiPValue" : 0,
        "Gi_Bin" : 3
      }
    },
    {
      "type" : "Feature",
      "id" : 34,
      "geometry" : {
        "type" : "Polygon",
        "coordinates" : [
          [
            [
              108.41353004528268,
              31.140088553962769
            ],
            [
              108.41376518914747,
              31.194203430491875
            ],
            [
              108.35081417467273,
              31.194390444442661
            ],
            [
              108.35061480409098,
              31.140275171567136
            ],
            [
              108.41353004528268,
              31.140088553962769
            ]
          ]
        ]
      },
      "properties" : {
        "FID" : 34,
        "SOURCE_ID" : 1774,
        "Join_Count" : 10457,
        "GiZScore" : 7.3293540621800002,
        "GiPValue" : 0,
        "Gi_Bin" : 3
      }
    },
    {
      "type" : "Feature",
      "id" : 35,
      "geometry" : {
        "type" : "Polygon",
        "coordinates" : [
          [
            [
              106.54956237545987,
              29.563263501533907
            ],
            [
              106.54878807466334,
              29.617375445580098
            ],
            [
              106.48686035148448,
              29.616683513616518
            ],
            [
              106.48766766402447,
              29.562573082251937
            ],
            [
              106.54956237545987,
              29.563263501533907
            ]
          ]
        ]
      },
      "properties" : {
        "FID" : 35,
        "SOURCE_ID" : 1780,
        "Join_Count" : 25544,
        "GiZScore" : 18.2152109118,
        "GiPValue" : 0,
        "Gi_Bin" : 3
      }
    },
    {
      "type" : "Feature",
      "id" : 36,
      "geometry" : {
        "type" : "Polygon",
        "coordinates" : [
          [
            [
              106.17822893130246,
              29.558688702753248
            ],
            [
              106.24011173481003,
              29.559523203037593
            ],
            [
              106.23917242676794,
              29.6136269524794
            ],
            [
              106.1772566382608,
              29.612790623973236
            ],
            [
              106.17822893130246,
              29.558688702753248
            ]
          ]
        ]
      },
      "properties" : {
        "FID" : 36,
        "SOURCE_ID" : 1789,
        "Join_Count" : 8999,
        "GiZScore" : 6.27786573774,
        "GiPValue" : 3.4325212016199998e-010,
        "Gi_Bin" : 3
      }
    },
    {
      "type" : "Feature",
      "id" : 37,
      "geometry" : {
        "type" : "Polygon",
        "coordinates" : [
          [
            [
              106.6114591986107,
              29.563925093120158
            ],
            [
              106.61071791430128,
              29.618038486706663
            ],
            [
              106.54878807466334,
              29.617375445580098
            ],
            [
              106.54956237545987,
              29.563263501533907
            ],
            [
              106.6114591986107,
              29.563925093120158
            ]
          ]
        ]
      },
      "properties" : {
        "FID" : 37,
        "SOURCE_ID" : 1872,
        "Join_Count" : 11634,
        "GiZScore" : 8.1842724057399998,
        "GiPValue" : 0,
        "Gi_Bin" : 3
      }
    },
    {
      "type" : "Feature",
      "id" : 38,
      "geometry" : {
        "type" : "Polygon",
        "coordinates" : [
          [
            [
              106.55110464662224,
              29.45503823519358
            ],
            [
              106.55033456453785,
              29.509151097887084
            ],
            [
              106.4884727748623,
              29.50846218971316
            ],
            [
              106.48927568892394,
              29.45435083655935
            ],
            [
              106.55110464662224,
              29.45503823519358
            ]
          ]
        ]
      },
      "properties" : {
        "FID" : 38,
        "SOURCE_ID" : 1918,
        "Join_Count" : 5427,
        "GiZScore" : 3.70665455438,
        "GiPValue" : 0.000210015092548,
        "Gi_Bin" : 3
      }
    },
    {
      "type" : "Feature",
      "id" : 39,
      "geometry" : {
        "type" : "Polygon",
        "coordinates" : [
          [
            [
              106.60997460373382,
              29.672151421652991
            ],
            [
              106.60922926234858,
              29.726263897412963
            ],
            [
              106.54723311892108,
              29.725597952661847
            ],
            [
              106.54801165740454,
              29.671486929473129
            ],
            [
              106.60997460373382,
              29.672151421652991
            ]
          ]
        ]
      },
      "properties" : {
        "FID" : 39,
        "SOURCE_ID" : 1940,
        "Join_Count" : 5398,
        "GiZScore" : 3.6819344152500002,
        "GiPValue" : 0.00023147096374,
        "Gi_Bin" : 3
      }
    },
    {
      "type" : "Feature",
      "id" : 40,
      "geometry" : {
        "type" : "Polygon",
        "coordinates" : [
          [
            [
              106.55263850861711,
              29.346811134889332
            ],
            [
              106.55187262641938,
              29.400924914008758
            ],
            [
              106.49007641111601,
              29.400239023351016
            ],
            [
              106.49087494632573,
              29.346126750650011
            ],
            [
              106.55263850861711,
              29.346811134889332
            ]
          ]
        ]
      },
      "properties" : {
        "FID" : 40,
        "SOURCE_ID" : 2026,
        "Join_Count" : 4008,
        "GiZScore" : 2.67856506575,
        "GiPValue" : 0.00739383653063,
        "Gi_Bin" : 3
      }
    },
    {
      "type" : "Feature",
      "id" : 41,
      "geometry" : {
        "type" : "Polygon",
        "coordinates" : [
          [
            [
              107.04170722957006,
              29.892472656625415
            ],
            [
              107.04222428597951,
              29.838353139625404
            ],
            [
              107.10430090247449,
              29.838788727447113
            ],
            [
              107.1038173468954,
              29.892909193494081
            ],
            [
              107.04170722957006,
              29.892472656625415
            ]
          ]
        ]
      },
      "properties" : {
        "FID" : 41,
        "SOURCE_ID" : 2027,
        "Join_Count" : 6053,
        "GiZScore" : 4.15356938565,
        "GiPValue" : 3.27328897113e-005,
        "Gi_Bin" : 3
      }
    },
    {
      "type" : "Feature",
      "id" : 42,
      "geometry" : {
        "type" : "Polygon",
        "coordinates" : [
          [
            [
              106.92776391570389,
              28.917329125193557
            ],
            [
              106.92720640622287,
              28.971454202333458
            ],
            [
              106.86565788219764,
              28.970949191967286
            ],
            [
              106.8662473609707,
              28.916825234614752
            ],
            [
              106.92776391570389,
              28.917329125193557
            ]
          ]
        ]
      },
      "properties" : {
        "FID" : 42,
        "SOURCE_ID" : 2096,
        "Join_Count" : 2930,
        "GiZScore" : 1.9010341341699999,
        "GiPValue" : 0.057297541785400002,
        "Gi_Bin" : 1
      }
    },
    {
      "type" : "Feature",
      "id" : 43,
      "geometry" : {
        "type" : "Polygon",
        "coordinates" : [
          [
            [
              108.77806366288245,
              29.514777587719106
            ],
            [
              108.77847823784964,
              29.568902333729834
            ],
            [
              108.71656428688158,
              29.569250820304653
            ],
            [
              108.71618267673341,
              29.515125311476922
            ],
            [
              108.77806366288245,
              29.514777587719106
            ]
          ]
        ]
      },
      "properties" : {
        "FID" : 43,
        "SOURCE_ID" : 2104,
        "Join_Count" : 4187,
        "GiZScore" : 2.8078268243500002,
        "GiPValue" : 0.00498770404622,
        "Gi_Bin" : 3
      }
    },
    {
      "type" : "Feature",
      "id" : 44,
      "geometry" : {
        "type" : "Polygon",
        "coordinates" : [
          [
            [
              106.4884727748623,
              29.50846218971316
            ],
            [
              106.48766766402447,
              29.562573082251937
            ],
            [
              106.42577515428805,
              29.561853838904334
            ],
            [
              106.42661318195972,
              29.507744520538871
            ],
            [
              106.4884727748623,
              29.50846218971316
            ]
          ]
        ]
      },
      "properties" : {
        "FID" : 44,
        "SOURCE_ID" : 2110,
        "Join_Count" : 31406,
        "GiZScore" : 22.4428596423,
        "GiPValue" : 0,
        "Gi_Bin" : 3
      }
    },
    {
      "type" : "Feature",
      "id" : 45,
      "geometry" : {
        "type" : "Polygon",
        "coordinates" : [
          [
            [
              107.84805274169196,
              30.653596532689047
            ],
            [
              107.84796798647,
              30.707716708979003
            ],
            [
              107.78533413992137,
              30.707628269906394
            ],
            [
              107.7854538118734,
              30.653508282794274
            ],
            [
              107.84805274169196,
              30.653596532689047
            ]
          ]
        ]
      },
      "properties" : {
        "FID" : 45,
        "SOURCE_ID" : 2125,
        "Join_Count" : 3863,
        "GiZScore" : 2.5738694765200001,
        "GiPValue" : 0.010056820453,
        "Gi_Bin" : 2
      }
    },
    {
      "type" : "Feature",
      "id" : 46,
      "geometry" : {
        "type" : "Polygon",
        "coordinates" : [
          [
            [
              106.61071791430128,
              29.618038486706663
            ],
            [
              106.60997460373382,
              29.672151421652991
            ],
            [
              106.54801165740454,
              29.671486929473129
            ],
            [
              106.54878807466334,
              29.617375445580098
            ],
            [
              106.61071791430128,
              29.618038486706663
            ]
          ]
        ]
      },
      "properties" : {
        "FID" : 46,
        "SOURCE_ID" : 2314,
        "Join_Count" : 5481,
        "GiZScore" : 3.74288997272,
        "GiPValue" : 0.000181915897403,
        "Gi_Bin" : 3
      }
    },
    {
      "type" : "Feature",
      "id" : 47,
      "geometry" : {
        "type" : "Polygon",
        "coordinates" : [
          [
            [
              108.77277623603594,
              28.811115470824593
            ],
            [
              108.7731762970906,
              28.865245977382081
            ],
            [
              108.71168392940346,
              28.865584608396833
            ],
            [
              108.71131567923862,
              28.811453349121386
            ],
            [
              108.77277623603594,
              28.811115470824593
            ]
          ]
        ]
      },
      "properties" : {
        "FID" : 47,
        "SOURCE_ID" : 2360,
        "Join_Count" : 3810,
        "GiZScore" : 2.5355155016199999,
        "GiPValue" : 0.0112281958867,
        "Gi_Bin" : 2
      }
    },
    {
      "type" : "Feature",
      "id" : 48,
      "geometry" : {
        "type" : "Polygon",
        "coordinates" : [
          [
            [
              106.55033456453785,
              29.509151097887084
            ],
            [
              106.54956237545987,
              29.563263501533907
            ],
            [
              106.48766766402447,
              29.562573082251937
            ],
            [
              106.4884727748623,
              29.50846218971316
            ],
            [
              106.55033456453785,
              29.509151097887084
            ]
          ]
        ]
      },
      "properties" : {
        "FID" : 48,
        "SOURCE_ID" : 2542,
        "Join_Count" : 24650,
        "GiZScore" : 17.574739387600001,
        "GiPValue" : 0,
        "Gi_Bin" : 3
      }
    }
  ]
}