{
  "type" : "FeatureCollection",
  "crs" : {
    "type" : "name",
    "properties" : {
      "name" : "EPSG:4326"
    }
  },
  "features" : [
    {
      "type" : "Feature",
      "id" : 0,
      "geometry" : {
        "type" : "Polygon",
        "coordinates" : [
          [
            [
              106.45672112832068,
              29.562217063353557
            ],
            [
              106.4549333461236,
              29.679454056630579
            ],
            [
              106.32068315710222,
              29.677820326870787
            ],
            [
              106.32262610839578,
              29.56059105685134
            ],
            [
              106.45672112832068,
              29.562217063353557
            ]
          ]
        ]
      },
      "properties" : {
        "FID" : 0,
        "SOURCE_ID" : 33,
        "Join_Count" : 10486,
        "GiZScore" : 2.0222350917499998,
        "GiPValue" : 0.043152070602900001,
        "Gi_Bin" : 2
      }
    },
    {
      "type" : "Feature",
      "id" : 1,
      "geometry" : {
        "type" : "Polygon",
        "coordinates" : [
          [
            [
              105.52118436535928,
              29.430824339400473
            ],
            [
              105.52402320466648,
              29.313650250243931
            ],
            [
              105.6577289456214,
              29.316064055343716
            ],
            [
              105.65504305493786,
              29.433249664615932
            ],
            [
              105.52118436535928,
              29.430824339400473
            ]
          ]
        ]
      },
      "properties" : {
        "FID" : 1,
        "SOURCE_ID" : 64,
        "Join_Count" : 10774,
        "GiZScore" : 2.0838528100000002,
        "GiPValue" : 0.037173557937099998,
        "Gi_Bin" : 2
      }
    },
    {
      "type" : "Feature",
      "id" : 2,
      "geometry" : {
        "type" : "Polygon",
        "coordinates" : [
          [
            [
              107.79763089028798,
              29.805586080503993
            ],
            [
              107.79739410997333,
              29.922860776265928
            ],
            [
              107.6627656296552,
              29.922585183214462
            ],
            [
              107.66315974102019,
              29.805311784160665
            ],
            [
              107.79763089028798,
              29.805586080503993
            ]
          ]
        ]
      },
      "properties" : {
        "FID" : 2,
        "SOURCE_ID" : 92,
        "Join_Count" : 9302,
        "GiZScore" : 1.761981045,
        "GiPValue" : 0.078072500107499998,
        "Gi_Bin" : 1
      }
    },
    {
      "type" : "Feature",
      "id" : 3,
      "geometry" : {
        "type" : "Polygon",
        "coordinates" : [
          [
            [
              107.39136514540044,
              30.273415615877454
            ],
            [
              107.39063950952682,
              30.390676040640543
            ],
            [
              107.3346045722315,
              30.390402646530966
            ],
            [
              107.33449672894095,
              30.389627803680241
            ],
            [
              107.3341574884774,
              30.389058425805779
            ],
            [
              107.3334190785277,
              30.388319679509667
            ],
            [
              107.33276054096628,
              30.387340861891282
            ],
            [
              107.33235144566275,
              30.38677158923754
            ],
            [
              107.33176274675344,
              30.385972630632462
            ],
            [
              107.33109421142878,
              30.385173792536527
            ],
            [
              107.33031588956669,
              30.384455102021381
            ],
            [
              107.33001653583455,
              30.384175606219287
            ],
            [
              107.32943779511824,
              30.38357659388474
            ],
            [
              107.3290985321716,
              30.383237169959497
            ],
            [
              107.32804085300302,
              30.382038994204262
            ],
            [
              107.3275020817557,
              30.3811199850993
            ],
            [
              107.32670387408457,
              30.379981409214746
            ],
            [
              107.32583582056675,
              30.378782949273731
            ],
            [
              107.32490789378433,
              30.377584579264973
            ],
            [
              107.32384028250311,
              30.376216452327473
            ],
            [
              107.3229023687494,
              30.375128075700161
            ],
            [
              107.32131582346655,
              30.373820714154711
            ],
            [
              107.32044778613647,
              30.372672244828266
            ],
            [
              107.31925045484468,
              30.37136429962278
            ],
            [
              107.31813291949868,
              30.370336180270549
            ],
            [
              107.31769389295886,
              30.369906923965395
            ],
            [
              107.31699544798158,
              30.369198112502954
            ],
            [
              107.31566837329683,
              30.36806032802178
            ],
            [
              107.31427145906065,
              30.366862660383507
            ],
            [
              107.31261508681689,
              30.365665382151686
            ],
            [
              107.31141774383387,
              30.364637381510022
            ],
            [
              107.31098868088299,
              30.364358080860761
            ],
            [
              107.30996093115209,
              30.363669758652478
            ],
            [
              107.30952187133738,
              30.36350045048545
            ],
            [
              107.308444175958,
              30.363102144348545
            ],
            [
              107.30724675113669,
              30.36259404088235
            ],
            [
              107.30584981711542,
              30.361686315571042
            ],
            [
              107.3047422570496,
              30.360938124594838
            ],
            [
              107.30439302421875,
              30.360718691814213
            ],
            [
              107.30306601158725,
              30.359520919854617
            ],
            [
              107.30173900615029,
              30.358323147895014
            ],
            [
              107.29975304047048,
              30.35718603071081
            ],
            [
              107.29855401755395,
              30.356036341004359
            ],
            [
              107.29776462413814,
              30.355416511163142
            ],
            [
              107.29616586516261,
              30.354046870666583
            ],
            [
              107.29496683415215,
              30.352787181283421
            ],
            [
              107.29397765814245,
              30.35158746588888
            ],
            [
              107.29337819075097,
              30.350667675273034
            ],
            [
              107.29276873638817,
              30.349697892243963
            ],
            [
              107.29230917023212,
              30.348838081012676
            ],
            [
              107.29183956494404,
              30.34821822239309
            ],
            [
              107.29084034710439,
              30.347188467174071
            ],
            [
              107.29011093487179,
              30.346328664935978
            ],
            [
              107.28918169867649,
              30.345128934252951
            ],
            [
              107.28805260524359,
              30.343759242495086
            ],
            [
              107.28685352836771,
              30.34249952972954
            ],
            [
              107.28572437288159,
              30.34141977850004
            ],
            [
              107.2843353942631,
              30.340160067533134
            ],
            [
              107.28339616659987,
              30.338790356889486
            ],
            [
              107.28232700938406,
              30.337420647145219
            ],
            [
              107.28140778084446,
              30.335920953888952
            ],
            [
              107.28105807137297,
              30.33536106745937
            ],
            [
              107.28005894346553,
              30.333471442553115
            ],
            [
              107.27997901442006,
              30.33331147384547
            ],
            [
              107.2793295914875,
              30.33199173223273
            ],
            [
              107.27839039979717,
              30.330212079124166
            ],
            [
              107.27792085836099,
              30.32895231779526
            ],
            [
              107.2779210004539,
              30.328042479077222
            ],
            [
              107.27745145631974,
              30.326782715949609
            ],
            [
              107.27717187598135,
              30.32506302783651
            ],
            [
              107.27650255914585,
              30.323003407681203
            ],
            [
              107.27609302587251,
              30.321403699021523
            ],
            [
              107.27550353555978,
              30.320143932296659
            ],
            [
              107.27516378607993,
              30.319694017664865
            ],
            [
              107.27463420860194,
              30.31877418837815
            ],
            [
              107.27416461320639,
              30.317744376501814
            ],
            [
              107.27376499585797,
              30.3166045820359
            ],
            [
              107.27349528288107,
              30.315624756277543
            ],
            [
              107.27342543793367,
              30.31482489565246
            ],
            [
              107.27308575860093,
              30.313855068556606
            ],
            [
              107.27275599968972,
              30.313395152564279
            ],
            [
              107.27196647946954,
              30.31294524063042
            ],
            [
              107.2709671024499,
              30.312255371588211
            ],
            [
              107.27017762000122,
              30.311515506535432
            ],
            [
              107.26937818115816,
              30.31048569016253
            ],
            [
              107.26890854349456,
              30.309625840260363
            ],
            [
              107.26856886056453,
              30.308596016692878
            ],
            [
              107.26803928938176,
              30.307456213233721
            ],
            [
              107.26742976487179,
              30.306256417799478
            ],
            [
              107.26704011021297,
              30.305166602256921
            ],
            [
              107.26623073476065,
              30.303566872013562
            ],
            [
              107.26563120351727,
              30.302307082805669
            ],
            [
              107.26463188405427,
              30.300937310108861
            ],
            [
              107.26357245210704,
              30.299227381438524
            ],
            [
              107.26263274510518,
              30.297457204486474
            ],
            [
              107.26176299636523,
              30.295627022069496
            ],
            [
              107.26083323226794,
              30.293336793258451
            ],
            [
              107.26002343053693,
              30.291276586745138
            ],
            [
              107.25884370617217,
              30.288136273770085
            ],
            [
              107.25798387785373,
              30.285556015397852
            ],
            [
              107.2577838902144,
              30.284675928051691
            ],
            [
              107.25768389279749,
              30.284205881196513
            ],
            [
              107.25762389902377,
              30.28396585663905
            ],
            [
              107.25713389711171,
              30.281495609634703
            ],
            [
              107.25680394124896,
              30.280285489084115
            ],
            [
              107.25652392204142,
              30.27869533032527
            ],
            [
              107.25622980971229,
              30.277915682461266
            ],
            [
              107.25626900296093,
              30.27271795051729
            ],
            [
              107.39136514540044,
              30.273415615877454
            ]
          ]
        ]
      },
      "properties" : {
        "FID" : 3,
        "SOURCE_ID" : 155,
        "Join_Count" : 8844,
        "GiZScore" : 1.6618629089200001,
        "GiPValue" : 0.096540265134700001,
        "Gi_Bin" : 1
      }
    },
    {
      "type" : "Feature",
      "id" : 4,
      "geometry" : {
        "type" : "Polygon",
        "coordinates" : [
          [
            [
              107.12530761586359,
              29.802846678641838
            ],
            [
              107.12428433997978,
              29.92010842447419
            ],
            [
              106.98967682899148,
              29.91914571497378
            ],
            [
              106.99085733331923,
              29.801888498565216
            ],
            [
              107.12530761586359,
              29.802846678641838
            ]
          ]
        ]
      },
      "properties" : {
        "FID" : 4,
        "SOURCE_ID" : 158,
        "Join_Count" : 12351,
        "GiZScore" : 2.4286811689899999,
        "GiPValue" : 0.0151538519351,
        "Gi_Bin" : 2
      }
    },
    {
      "type" : "Feature",
      "id" : 5,
      "geometry" : {
        "type" : "Polygon",
        "coordinates" : [
          [
            [
              106.31676264501893,
              29.912272285202377
            ],
            [
              106.31478497098098,
              30.029494961969682
            ],
            [
              106.18007542919005,
              30.027700115411779
            ],
            [
              106.18221098633427,
              29.910485861426601
            ],
            [
              106.31676264501893,
              29.912272285202377
            ]
          ]
        ]
      },
      "properties" : {
        "FID" : 5,
        "SOURCE_ID" : 214,
        "Join_Count" : 11059,
        "GiZScore" : 2.1462124577399999,
        "GiPValue" : 0.031856032120899998,
        "Gi_Bin" : 2
      }
    },
    {
      "type" : "Feature",
      "id" : 6,
      "geometry" : {
        "type" : "Polygon",
        "coordinates" : [
          [
            [
              107.39492989261018,
              29.68708182672902
            ],
            [
              107.39422533148979,
              29.804352789976125
            ],
            [
              107.25976392387616,
              29.803668115895086
            ],
            [
              107.2606248420537,
              29.686400381915561
            ],
            [
              107.39492989261018,
              29.68708182672902
            ]
          ]
        ]
      },
      "properties" : {
        "FID" : 6,
        "SOURCE_ID" : 258,
        "Join_Count" : 10745,
        "GiZScore" : 2.0776103913399999,
        "GiPValue" : 0.037745258319600003,
        "Gi_Bin" : 2
      }
    },
    {
      "type" : "Feature",
      "id" : 7,
      "geometry" : {
        "type" : "Polygon",
        "coordinates" : [
          [
            [
              106.32838641268084,
              29.208890153267287
            ],
            [
              106.32647768099613,
              29.32612596418868
            ],
            [
              106.19270161054115,
              29.324381368394885
            ],
            [
              106.19476272556129,
              29.207153866829298
            ],
            [
              106.32838641268084,
              29.208890153267287
            ]
          ]
        ]
      },
      "properties" : {
        "FID" : 7,
        "SOURCE_ID" : 289,
        "Join_Count" : 14187,
        "GiZScore" : 2.8302107780500001,
        "GiPValue" : 0.0046517347435200002,
        "Gi_Bin" : 3
      }
    },
    {
      "type" : "Feature",
      "id" : 8,
      "geometry" : {
        "type" : "Polygon",
        "coordinates" : [
          [
            [
              105.92518714541313,
              29.320490400512004
            ],
            [
              105.92280737794559,
              29.437697136336688
            ],
            [
              105.78891769502445,
              29.43554061572685
            ],
            [
              105.79145056031018,
              29.318344124114631
            ],
            [
              105.92518714541313,
              29.320490400512004
            ]
          ]
        ]
      },
      "properties" : {
        "FID" : 8,
        "SOURCE_ID" : 331,
        "Join_Count" : 13564,
        "GiZScore" : 2.6940430213100002,
        "GiPValue" : 0.0070591052516200004,
        "Gi_Bin" : 3
      }
    },
    {
      "type" : "Feature",
      "id" : 9,
      "geometry" : {
        "type" : "Polygon",
        "coordinates" : [
          [
            [
              108.870343239295,
              29.451057384057467
            ],
            [
              108.8703518614531,
              29.452067661892887
            ],
            [
              108.86972933893793,
              29.452273975063971
            ],
            [
              108.86945901981794,
              29.452533493326101
            ],
            [
              108.86879822405888,
              29.453652121348401
            ],
            [
              108.86807731761417,
              29.456020167596701
            ],
            [
              108.86780689327357,
              29.459528386925573
            ],
            [
              108.86693577396689,
              29.462855838925858
            ],
            [
              108.86715601973458,
              29.463166023193494
            ],
            [
              108.86839745467887,
              29.463397666968834
            ],
            [
              108.86911828108386,
              29.463768526696185
            ],
            [
              108.86956876678522,
              29.465018657185343
            ],
            [
              108.86947864392432,
              29.465618291850717
            ],
            [
              108.8684473823409,
              29.467556074553279
            ],
            [
              108.86565399723422,
              29.471260687830515
            ],
            [
              108.86488307319536,
              29.471879362042959
            ],
            [
              108.86394195245919,
              29.472397838289687
            ],
            [
              108.86306090193915,
              29.472906403108095
            ],
            [
              108.86244015119205,
              29.473545279690946
            ],
            [
              108.86228996081309,
              29.47392491770086
            ],
            [
              108.86221982448536,
              29.475354248899514
            ],
            [
              108.86280039891932,
              29.478243905531897
            ],
            [
              108.8643720226508,
              29.484593567039546
            ],
            [
              108.86559332357309,
              29.488793596147612
            ],
            [
              108.86665451549358,
              29.490864252783073
            ],
            [
              108.86720515239591,
              29.491404807385997
            ],
            [
              108.86872694739077,
              29.491946719065865
            ],
            [
              108.8706916606105,
              29.491841578538761
            ],
            [
              108.871347009983,
              29.568325496944944
            ],
            [
              108.73720239096673,
              29.56913786460191
            ],
            [
              108.73635311448514,
              29.451865901251193
            ],
            [
              108.870343239295,
              29.451057384057467
            ]
          ]
        ]
      },
      "properties" : {
        "FID" : 9,
        "SOURCE_ID" : 367,
        "Join_Count" : 9381,
        "GiZScore" : 1.77921681181,
        "GiPValue" : 0.075204223163199996,
        "Gi_Bin" : 1
      }
    },
    {
      "type" : "Feature",
      "id" : 10,
      "geometry" : {
        "type" : "Polygon",
        "coordinates" : [
          [
            [
              106.458498363543,
              29.44497790131312
            ],
            [
              106.45672112832068,
              29.562217063353557
            ],
            [
              106.32262610839578,
              29.56059105685134
            ],
            [
              106.32455759788546,
              29.443359600675237
            ],
            [
              106.458498363543,
              29.44497790131312
            ]
          ]
        ]
      },
      "properties" : {
        "FID" : 10,
        "SOURCE_ID" : 382,
        "Join_Count" : 18104,
        "GiZScore" : 3.68829810658,
        "GiPValue" : 0.000225759057371,
        "Gi_Bin" : 3
      }
    },
    {
      "type" : "Feature",
      "id" : 11,
      "geometry" : {
        "type" : "Polygon",
        "coordinates" : [
          [
            [
              108.47621944750884,
              31.094775513246642
            ],
            [
              108.47680603612842,
              31.212023659867214
            ],
            [
              108.34038686941827,
              31.212456962301999
            ],
            [
              108.33996810044148,
              31.095206827958329
            ],
            [
              108.47621944750884,
              31.094775513246642
            ]
          ]
        ]
      },
      "properties" : {
        "FID" : 11,
        "SOURCE_ID" : 435,
        "Join_Count" : 13464,
        "GiZScore" : 2.6720910469799999,
        "GiPValue" : 0.0075380192859399999,
        "Gi_Bin" : 3
      }
    },
    {
      "type" : "Feature",
      "id" : 12,
      "geometry" : {
        "type" : "Polygon",
        "coordinates" : [
          [
            [
              106.32262610839578,
              29.56059105685134
            ],
            [
              106.32068315710222,
              29.677820326870787
            ],
            [
              106.18644448570569,
              29.676050691065605
            ],
            [
              106.18854255019541,
              29.558829786507562
            ],
            [
              106.32262610839578,
              29.56059105685134
            ]
          ]
        ]
      },
      "properties" : {
        "FID" : 12,
        "SOURCE_ID" : 508,
        "Join_Count" : 13316,
        "GiZScore" : 2.6399171858499999,
        "GiPValue" : 0.0082926288302200002,
        "Gi_Bin" : 3
      }
    },
    {
      "type" : "Feature",
      "id" : 13,
      "geometry" : {
        "type" : "Polygon",
        "coordinates" : [
          [
            [
              106.45672112832068,
              29.562217063353557
            ],
            [
              106.458498363543,
              29.44497790131312
            ],
            [
              106.59244962509437,
              29.446461538993621
            ],
            [
              106.59082669514737,
              29.563707765886562
            ],
            [
              106.45672112832068,
              29.562217063353557
            ]
          ]
        ]
      },
      "properties" : {
        "FID" : 13,
        "SOURCE_ID" : 518,
        "Join_Count" : 85720,
        "GiZScore" : 18.472479976700001,
        "GiPValue" : 0,
        "Gi_Bin" : 3
      }
    },
    {
      "type" : "Feature",
      "id" : 14,
      "geometry" : {
        "type" : "Polygon",
        "coordinates" : [
          [
            [
              106.59082669514737,
              29.563707765886562
            ],
            [
              106.58919413349298,
              29.680951839965584
            ],
            [
              106.4549333461236,
              29.679454056630579
            ],
            [
              106.45672112832068,
              29.562217063353557
            ],
            [
              106.59082669514737,
              29.563707765886562
            ]
          ]
        ]
      },
      "properties" : {
        "FID" : 14,
        "SOURCE_ID" : 535,
        "Join_Count" : 49205,
        "GiZScore" : 10.488715837000001,
        "GiPValue" : 0,
        "Gi_Bin" : 3
      }
    },
    {
      "type" : "Feature",
      "id" : 15,
      "geometry" : {
        "type" : "Polygon",
        "coordinates" : [
          [
            [
              108.47448013911156,
              30.743018223341828
            ],
            [
              108.47505651628153,
              30.860272790321556
            ],
            [
              108.33913787727775,
              30.860700143865753
            ],
            [
              108.33872639841535,
              30.743443603373876
            ],
            [
              108.47448013911156,
              30.743018223341828
            ]
          ]
        ]
      },
      "properties" : {
        "FID" : 15,
        "SOURCE_ID" : 556,
        "Join_Count" : 22752,
        "GiZScore" : 4.70296184604,
        "GiPValue" : 2.5641434985300001e-006,
        "Gi_Bin" : 3
      }
    },
    {
      "type" : "Feature",
      "id" : 16,
      "geometry" : {
        "type" : "Polygon",
        "coordinates" : [
          [
            [
              107.13132175479092,
              29.099231994741654
            ],
            [
              107.13033419634723,
              29.216506345402777
            ],
            [
              106.99665626132125,
              29.215570659275606
            ],
            [
              106.99779556135961,
              29.098300777277142
            ],
            [
              107.13132175479092,
              29.099231994741654
            ]
          ]
        ]
      },
      "properties" : {
        "FID" : 16,
        "SOURCE_ID" : 588,
        "Join_Count" : 8842,
        "GiZScore" : 1.66142474839,
        "GiPValue" : 0.096628170767900007,
        "Gi_Bin" : 1
      }
    },
    {
      "type" : "Feature",
      "id" : 17,
      "geometry" : {
        "type" : "Polygon",
        "coordinates" : [
          [
            [
              106.72346459949121,
              29.68231363985063
            ],
            [
              106.72197854680107,
              29.799562008262008
            ],
            [
              106.58755189314243,
              29.798193755653067
            ],
            [
              106.58919413349298,
              29.680951839965584
            ],
            [
              106.72346459949121,
              29.68231363985063
            ]
          ]
        ]
      },
      "properties" : {
        "FID" : 17,
        "SOURCE_ID" : 600,
        "Join_Count" : 12073,
        "GiZScore" : 2.3680152996300001,
        "GiPValue" : 0.017883796334900001,
        "Gi_Bin" : 2
      }
    }
  ]
}