{
  "type" : "FeatureCollection",
  "crs" : {
    "type" : "name",
    "properties" : {
      "name" : "EPSG:4326"
    }
  },
  "features" : [
    {
      "type" : "Feature",
      "id" : 0,
      "geometry" : {
        "type" : "Polygon",
        "coordinates" : [
          [
            [
              106.82796507965308,
              28.672913884846015
            ],
            [
              106.82724609175358,
              28.737403637487994
            ],
            [
              106.82683800896699,
              28.737634485743001
            ],
            [
              106.82538670463278,
              28.739401252465889
            ],
            [
              106.82445586764426,
              28.741048869809553
            ],
            [
              106.8237552373144,
              28.744485759410345
            ],
            [
              106.82331484200641,
              28.747753141194544
            ],
            [
              106.82259419366714,
              28.749990720095688
            ],
            [
              106.82256416710271,
              28.750100609155822
            ],
            [
              106.82175343817067,
              28.752148166704561
            ],
            [
              106.82122296047127,
              28.753316672026859
            ],
            [
              106.82041223153931,
              28.755114379025425
            ],
            [
              106.82006191682405,
              28.756812835943656
            ],
            [
              106.82015199831615,
              28.75947137760204
            ],
            [
              106.82140312255615,
              28.761102274750222
            ],
            [
              106.82205370741275,
              28.76196273349343
            ],
            [
              106.8240454989007,
              28.764504195112572
            ],
            [
              106.82654774827999,
              28.766856534701382
            ],
            [
              106.82691525152838,
              28.767007266270262
            ],
            [
              106.82604899710616,
              28.844308771457772
            ],
            [
              106.63139594142741,
              28.842473968652396
            ],
            [
              106.63362950603775,
              28.67109198731459
            ],
            [
              106.82796507965308,
              28.672913884846015
            ]
          ]
        ]
      },
      "properties" : {
        "FID" : 0,
        "SOURCE_ID" : 13,
        "Join_Count" : 11,
        "GiZScore" : 3.3705212519100001,
        "GiPValue" : 0.00075026118774799999,
        "NNeighbors" : 6,
        "Gi_Bin" : 3
      }
    },
    {
      "type" : "Feature",
      "id" : 1,
      "geometry" : {
        "type" : "Polygon",
        "coordinates" : [
          [
            [
              106.42633409371518,
              29.525781011382918
            ],
            [
              106.42367004780364,
              29.697125108778465
            ],
            [
              106.22743089561324,
              29.694643863305952
            ],
            [
              106.23042619285417,
              29.523316893741026
            ],
            [
              106.42633409371518,
              29.525781011382918
            ]
          ]
        ]
      },
      "properties" : {
        "FID" : 1,
        "SOURCE_ID" : 44,
        "Join_Count" : 7,
        "GiZScore" : 2.0156090871000001,
        "GiPValue" : 0.0438408688149,
        "NNeighbors" : 5,
        "Gi_Bin" : 2
      }
    },
    {
      "type" : "Feature",
      "id" : 2,
      "geometry" : {
        "type" : "Polygon",
        "coordinates" : [
          [
            [
              106.04111108116234,
              29.177934400220668
            ],
            [
              106.03784180728803,
              29.349251731262079
            ],
            [
              105.8423163658654,
              29.346231922092471
            ],
            [
              105.84591083006934,
              29.174935587563517
            ],
            [
              106.04111108116234,
              29.177934400220668
            ]
          ]
        ]
      },
      "properties" : {
        "FID" : 2,
        "SOURCE_ID" : 72,
        "Join_Count" : 7,
        "GiZScore" : 2.0146812918600001,
        "GiPValue" : 0.043938053656499998,
        "NNeighbors" : 5,
        "Gi_Bin" : 2
      }
    },
    {
      "type" : "Feature",
      "id" : 3,
      "geometry" : {
        "type" : "Polygon",
        "coordinates" : [
          [
            [
              106.42897519345087,
              29.354432276781658
            ],
            [
              106.42633409371518,
              29.525781011382918
            ],
            [
              106.23042619285417,
              29.523316893741026
            ],
            [
              106.23339569275566,
              29.351985230713726
            ],
            [
              106.42897519345087,
              29.354432276781658
            ]
          ]
        ]
      },
      "properties" : {
        "FID" : 3,
        "SOURCE_ID" : 75,
        "Join_Count" : 12,
        "GiZScore" : 3.7101375990499998,
        "GiPValue" : 0.00020714662922600001,
        "NNeighbors" : 5,
        "Gi_Bin" : 3
      }
    },
    {
      "type" : "Feature",
      "id" : 4,
      "geometry" : {
        "type" : "Polygon",
        "coordinates" : [
          [
            [
              106.81821587979265,
              29.529843390024254
            ],
            [
              106.8162148073598,
              29.701215726402886
            ],
            [
              106.61993230954708,
              29.699315768378188
            ],
            [
              106.62226494041317,
              29.527956548360379
            ],
            [
              106.81821587979265,
              29.529843390024254
            ]
          ]
        ]
      },
      "properties" : {
        "FID" : 4,
        "SOURCE_ID" : 81,
        "Join_Count" : 6,
        "GiZScore" : 1.6764464703599999,
        "GiPValue" : 0.093650773008499999,
        "NNeighbors" : 5,
        "Gi_Bin" : 1
      }
    },
    {
      "type" : "Feature",
      "id" : 5,
      "geometry" : {
        "type" : "Polygon",
        "coordinates" : [
          [
            [
              106.43159350869732,
              29.183078922976861
            ],
            [
              106.42897519345087,
              29.354432276781658
            ],
            [
              106.23339569275566,
              29.351985230713726
            ],
            [
              106.23633957705394,
              29.180648892810581
            ],
            [
              106.43159350869732,
              29.183078922976861
            ]
          ]
        ]
      },
      "properties" : {
        "FID" : 5,
        "SOURCE_ID" : 94,
        "Join_Count" : 12,
        "GiZScore" : 3.70981645612,
        "GiPValue" : 0.00020740955861099999,
        "NNeighbors" : 5,
        "Gi_Bin" : 3
      }
    },
    {
      "type" : "Feature",
      "id" : 6,
      "geometry" : {
        "type" : "Polygon",
        "coordinates" : [
          [
            [
              107.40515495682658,
              29.705170464083018
            ],
            [
              107.4041404896266,
              29.876565632929996
            ],
            [
              107.20747979567095,
              29.87553120422557
            ],
            [
              107.20882900848528,
              29.704143151597716
            ],
            [
              107.40515495682658,
              29.705170464083018
            ]
          ]
        ]
      },
      "properties" : {
        "FID" : 6,
        "SOURCE_ID" : 135,
        "Join_Count" : 7,
        "GiZScore" : 2.0147348646799998,
        "GiPValue" : 0.043932437058700001,
        "NNeighbors" : 5,
        "Gi_Bin" : 2
      }
    },
    {
      "type" : "Feature",
      "id" : 7,
      "geometry" : {
        "type" : "Polygon",
        "coordinates" : [
          [
            [
              106.41553858547142,
              30.211129399774016
            ],
            [
              106.2938601533002,
              30.209601960952089
            ],
            [
              106.29399592267373,
              30.209536911899015
            ],
            [
              106.29446580315435,
              30.209276952969056
            ],
            [
              106.29513561371768,
              30.208727010343292
            ],
            [
              106.29561543980077,
              30.207947050815793
            ],
            [
              106.29492549251751,
              30.207086983277698
            ],
            [
              106.29481551172655,
              30.207066972462879
            ],
            [
              106.29323580758647,
              30.206866824744232
            ],
            [
              106.29209595916126,
              30.206106712354927
            ],
            [
              106.2925157761822,
              30.205106744480705
            ],
            [
              106.29312555520029,
              30.204116795953428
            ],
            [
              106.29323547573665,
              30.203546802043316
            ],
            [
              106.29326541776487,
              30.203026801445784
            ],
            [
              106.29234553811615,
              30.202386708080155
            ],
            [
              106.29112573906166,
              30.201956584828565
            ],
            [
              106.2894860798188,
              30.202086426247597
            ],
            [
              106.2872366415578,
              30.203216220252386
            ],
            [
              106.28517719407235,
              30.204626041558647
            ],
            [
              106.28312766071305,
              30.205195855604309
            ],
            [
              106.28147789039241,
              30.204195680886031
            ],
            [
              106.2811278229907,
              30.20282562220472
            ],
            [
              106.28092768876189,
              30.20107556938207
            ],
            [
              106.28071763591021,
              30.199445539180331
            ],
            [
              106.28016776972686,
              30.198285507270377
            ],
            [
              106.27816818291534,
              30.197795321896663
            ],
            [
              106.27638854959196,
              30.197485155615478
            ],
            [
              106.27579866627546,
              30.197595095037681
            ],
            [
              106.27494883302228,
              30.197825006718748
            ],
            [
              106.27461888615272,
              30.198354961012686
            ],
            [
              106.2746388421089,
              30.199914923235163
            ],
            [
              106.27467917670272,
              30.203475011862327
            ],
            [
              106.27514943130126,
              30.206965144026245
            ],
            [
              106.27619937630021,
              30.208515278457419
            ],
            [
              106.2761708018332,
              30.209370498884802
            ],
            [
              106.26761734034153,
              30.209257721890442
            ],
            [
              106.26707121616374,
              30.208674449466351
            ],
            [
              106.2669612272789,
              30.208564435400444
            ],
            [
              106.26648119255304,
              30.207254348009823
            ],
            [
              106.26653102938354,
              30.205724301735188
            ],
            [
              106.26696080459749,
              30.204334296090973
            ],
            [
              106.2677404808386,
              30.202654316643468
            ],
            [
              106.26808031665338,
              30.201684318676424
            ],
            [
              106.26838017490518,
              30.200864322230771
            ],
            [
              106.26867003899117,
              30.199804331804501
            ],
            [
              106.26857008204371,
              30.199064344443968
            ],
            [
              106.26752035288206,
              30.197234300522613
            ],
            [
              106.26594072338573,
              30.195724198513009
            ],
            [
              106.26466100789924,
              30.195074098391004
            ],
            [
              106.26317131240619,
              30.195093956321106
            ],
            [
              106.26158161320097,
              30.195733780789396
            ],
            [
              106.26084173016176,
              30.19661367568062
            ],
            [
              106.25935195642768,
              30.198493455708437
            ],
            [
              106.25838209695625,
              30.200103300626896
            ],
            [
              106.25730232504232,
              30.19951321046636
            ],
            [
              106.25683248593054,
              30.197973230280414
            ],
            [
              106.25628264852548,
              30.196783228463289
            ],
            [
              106.25506291062487,
              30.196463124673528
            ],
            [
              106.25433303883877,
              30.196903034347603
            ],
            [
              106.25324319271925,
              30.198342861533895
            ],
            [
              106.25173348011607,
              30.198702696472321
            ],
            [
              106.25110362463261,
              30.198342651991815
            ],
            [
              106.24994397223657,
              30.196062652069774
            ],
            [
              106.24913414352596,
              30.195932580424309
            ],
            [
              106.24853426334562,
              30.195972521114992
            ],
            [
              106.24812434066587,
              30.196102474949335
            ],
            [
              106.24614466934105,
              30.197482211235116
            ],
            [
              106.24559475999024,
              30.197862137028046
            ],
            [
              106.24374508926451,
              30.198661911318197
            ],
            [
              106.2423353938634,
              30.198291793531492
            ],
            [
              106.24177555689647,
              30.197431788046636
            ],
            [
              106.24226552553364,
              30.196251904501828
            ],
            [
              106.24354534174422,
              30.194882103926027
            ],
            [
              106.24482515885404,
              30.193442304618713
            ],
            [
              106.24590499551921,
              30.192342465232631
            ],
            [
              106.24580506824934,
              30.191382508196231
            ],
            [
              106.2453152174234,
              30.190522509905975
            ],
            [
              106.2445554054077,
              30.190002470637584
            ],
            [
              106.24365560851959,
              30.189742403788962
            ],
            [
              106.24242588814427,
              30.189382314342371
            ],
            [
              106.2406262925694,
              30.188942179837792
            ],
            [
              106.23882670958506,
              30.188332057278672
            ],
            [
              106.23810685984374,
              30.188361992112274
            ],
            [
              106.23681715468803,
              30.188001900867114
            ],
            [
              106.23565740966177,
              30.187861808076036
            ],
            [
              106.23396777419352,
              30.187761665868198
            ],
            [
              106.23182823578452,
              30.187651486327063
            ],
            [
              106.22999859565873,
              30.18806129749094
            ],
            [
              106.22886878456683,
              30.188761148108526
            ],
            [
              106.22824883151843,
              30.189931009608479
            ],
            [
              106.22811880483904,
              30.190680944370115
            ],
            [
              106.22789877580796,
              30.191730848899631
            ],
            [
              106.22812866950257,
              30.192540811609209
            ],
            [
              106.22860853425652,
              30.193050818940215
            ],
            [
              106.22927835561165,
              30.193610842066736
            ],
            [
              106.22987819622182,
              30.194120862887594
            ],
            [
              106.2307379885674,
              30.194570912417706
            ],
            [
              106.23206769017185,
              30.194951011779839
            ],
            [
              106.233657316532,
              30.195671115129926
            ],
            [
              106.23445711600316,
              30.196231154444256
            ],
            [
              106.23473702999,
              30.196681152713101
            ],
            [
              106.23473700031235,
              30.197141122664721
            ],
            [
              106.23448701666258,
              30.197661063907056
            ],
            [
              106.23442700580176,
              30.198011035081265
            ],
            [
              106.23463694174153,
              30.198351033673301
            ],
            [
              106.23496686073209,
              30.198571051912545
            ],
            [
              106.23543674840725,
              30.19885108011329
            ],
            [
              106.23550673274957,
              30.198871085532225
            ],
            [
              106.2358465964433,
              30.199931051676753
            ],
            [
              106.23618666158524,
              30.201411168490665
            ],
            [
              106.23646674104731,
              30.202771281569419
            ],
            [
              106.23617690034376,
              30.203781318253291
            ],
            [
              106.23606694653239,
              30.204021323025703
            ],
            [
              106.23532725864612,
              30.205671358646335
            ],
            [
              106.23418771778898,
              30.207991403580472
            ],
            [
              106.23414773303153,
              30.208061404110548
            ],
            [
              106.23358589696568,
              30.208803489364382
            ],
            [
              106.21828836801885,
              30.208596427335266
            ],
            [
              106.22136217070845,
              30.0372836483605
            ],
            [
              106.41827246050876,
              30.03979932063184
            ],
            [
              106.41553858547142,
              30.211129399774016
            ]
          ]
        ]
      },
      "properties" : {
        "FID" : 7,
        "SOURCE_ID" : 173,
        "Join_Count" : 6,
        "GiZScore" : 1.6755979696700001,
        "GiPValue" : 0.093816966773399998,
        "NNeighbors" : 4,
        "Gi_Bin" : 1
      }
    },
    {
      "type" : "Feature",
      "id" : 8,
      "geometry" : {
        "type" : "Polygon",
        "coordinates" : [
          [
            [
              106.22440961701092,
              29.865966120953544
            ],
            [
              106.22743089561324,
              29.694643863305952
            ],
            [
              106.42367004780364,
              29.697125108778465
            ],
            [
              106.42098289199558,
              29.86846455110371
            ],
            [
              106.22440961701092,
              29.865966120953544
            ]
          ]
        ]
      },
      "properties" : {
        "FID" : 8,
        "SOURCE_ID" : 201,
        "Join_Count" : 7,
        "GiZScore" : 2.0148419123200001,
        "GiPValue" : 0.043921215952100003,
        "NNeighbors" : 5,
        "Gi_Bin" : 2
      }
    },
    {
      "type" : "Feature",
      "id" : 9,
      "geometry" : {
        "type" : "Polygon",
        "coordinates" : [
          [
            [
              106.8162148073598,
              29.701215726402886
            ],
            [
              106.81419637388895,
              29.87258350147405
            ],
            [
              106.61757944231084,
              29.870670383531959
            ],
            [
              106.61993230954708,
              29.699315768378188
            ],
            [
              106.8162148073598,
              29.701215726402886
            ]
          ]
        ]
      },
      "properties" : {
        "FID" : 9,
        "SOURCE_ID" : 232,
        "Join_Count" : 7,
        "GiZScore" : 2.0148954222,
        "GiPValue" : 0.0439156077678,
        "NNeighbors" : 5,
        "Gi_Bin" : 2
      }
    },
    {
      "type" : "Feature",
      "id" : 10,
      "geometry" : {
        "type" : "Polygon",
        "coordinates" : [
          [
            [
              106.62226494041317,
              29.527956548360379
            ],
            [
              106.61993230954708,
              29.699315768378188
            ],
            [
              106.42367004780364,
              29.697125108778465
            ],
            [
              106.42633409371518,
              29.525781011382918
            ],
            [
              106.62226494041317,
              29.527956548360379
            ]
          ]
        ]
      },
      "properties" : {
        "FID" : 10,
        "SOURCE_ID" : 261,
        "Join_Count" : 38,
        "GiZScore" : 12.5236912204,
        "GiPValue" : 0,
        "NNeighbors" : 5,
        "Gi_Bin" : 3
      }
    },
    {
      "type" : "Feature",
      "id" : 11,
      "geometry" : {
        "type" : "Polygon",
        "coordinates" : [
          [
            [
              107.40616069725721,
              29.533770824628924
            ],
            [
              107.40515495682658,
              29.705170464083018
            ],
            [
              107.20882900848528,
              29.704143151597716
            ],
            [
              107.21016661531866,
              29.532750604796806
            ],
            [
              107.40616069725721,
              29.533770824628924
            ]
          ]
        ]
      },
      "properties" : {
        "FID" : 11,
        "SOURCE_ID" : 264,
        "Join_Count" : 6,
        "GiZScore" : 1.6757685019599999,
        "GiPValue" : 0.093783546050600006,
        "NNeighbors" : 5,
        "Gi_Bin" : 1
      }
    },
    {
      "type" : "Feature",
      "id" : 12,
      "geometry" : {
        "type" : "Polygon",
        "coordinates" : [
          [
            [
              106.61993230954708,
              29.699315768378188
            ],
            [
              106.61757944231084,
              29.870670383531959
            ],
            [
              106.42098289199558,
              29.86846455110371
            ],
            [
              106.42367004780364,
              29.697125108778465
            ],
            [
              106.61993230954708,
              29.699315768378188
            ]
          ]
        ]
      },
      "properties" : {
        "FID" : 12,
        "SOURCE_ID" : 282,
        "Join_Count" : 8,
        "GiZScore" : 2.3545219259999999,
        "GiPValue" : 0.018546549505900001,
        "NNeighbors" : 5,
        "Gi_Bin" : 2
      }
    },
    {
      "type" : "Feature",
      "id" : 13,
      "geometry" : {
        "type" : "Polygon",
        "coordinates" : [
          [
            [
              106.62457747830089,
              29.356592740821601
            ],
            [
              106.62226494041317,
              29.527956548360379
            ],
            [
              106.42633409371518,
              29.525781011382918
            ],
            [
              106.42897519345087,
              29.354432276781658
            ],
            [
              106.62457747830089,
              29.356592740821601
            ]
          ]
        ]
      },
      "properties" : {
        "FID" : 13,
        "SOURCE_ID" : 291,
        "Join_Count" : 14,
        "GiZScore" : 4.3884271499700001,
        "GiPValue" : 1.14173365723e-005,
        "NNeighbors" : 5,
        "Gi_Bin" : 3
      }
    },
    {
      "type" : "Feature",
      "id" : 14,
      "geometry" : {
        "type" : "Polygon",
        "coordinates" : [
          [
            [
              108.58929120064997,
              30.733527864914887
            ],
            [
              108.59033845158396,
              30.90489625044664
            ],
            [
              108.39159801315681,
              30.905650501595225
            ],
            [
              108.39090329711092,
              30.734277032560342
            ],
            [
              108.58929120064997,
              30.733527864914887
            ]
          ]
        ]
      },
      "properties" : {
        "FID" : 14,
        "SOURCE_ID" : 294,
        "Join_Count" : 7,
        "GiZScore" : 2.0146813408600002,
        "GiPValue" : 0.043938048519600002,
        "NNeighbors" : 5,
        "Gi_Bin" : 2
      }
    }
  ]
}