{
  "type" : "FeatureCollection",
  "crs" : {
    "type" : "name",
    "properties" : {
      "name" : "EPSG:4326"
    }
  },
  "features" : [
    {
      "type" : "Feature",
      "id" : 0,
      "geometry" : {
        "type" : "Polygon",
        "coordinates" : [
          [
            [
              106.6114591986107,
              29.563925093120158
            ],
            [
              106.6099746037338,
              29.672151421652991
            ],
            [
              106.48605083229683,
              29.670793483249202
            ],
            [
              106.4876676640245,
              29.562573082251937
            ],
            [
              106.6114591986107,
              29.563925093120158
            ]
          ]
        ]
      },
      "properties" : {
        "FID" : 0,
        "SOURCE_ID" : 22,
        "Join_Count" : 3988,
        "GiZScore" : 19.071958066000001,
        "GiPValue" : 0,
        "NNeighbors" : 5,
        "Gi_Bin" : 3
      }
    },
    {
      "type" : "Feature",
      "id" : 1,
      "geometry" : {
        "type" : "Polygon",
        "coordinates" : [
          [
            [
              106.48927568892397,
              29.45435083655935
            ],
            [
              106.4876676640245,
              29.562573082251937
            ],
            [
              106.36388493621453,
              29.561105775272473
            ],
            [
              106.36562443868941,
              29.452889949049222
            ],
            [
              106.48927568892397,
              29.45435083655935
            ]
          ]
        ]
      },
      "properties" : {
        "FID" : 1,
        "SOURCE_ID" : 205,
        "Join_Count" : 1763,
        "GiZScore" : 8.2859986838000008,
        "GiPValue" : 0,
        "NNeighbors" : 5,
        "Gi_Bin" : 3
      }
    },
    {
      "type" : "Feature",
      "id" : 2,
      "geometry" : {
        "type" : "Polygon",
        "coordinates" : [
          [
            [
              106.7339064984118,
              29.67339353003711
            ],
            [
              106.73254677697264,
              29.781623455239995
            ],
            [
              106.60848188556777,
              29.780375913441901
            ],
            [
              106.6099746037338,
              29.672151421652991
            ],
            [
              106.7339064984118,
              29.67339353003711
            ]
          ]
        ]
      },
      "properties" : {
        "FID" : 2,
        "SOURCE_ID" : 213,
        "Join_Count" : 414,
        "GiZScore" : 1.74528750088,
        "GiPValue" : 0.080934836542200003,
        "NNeighbors" : 5,
        "Gi_Bin" : 1
      }
    },
    {
      "type" : "Feature",
      "id" : 3,
      "geometry" : {
        "type" : "Polygon",
        "coordinates" : [
          [
            [
              106.61293570660466,
              29.455696932218203
            ],
            [
              106.6114591986107,
              29.563925093120158
            ],
            [
              106.4876676640245,
              29.562573082251937
            ],
            [
              106.48927568892397,
              29.45435083655935
            ],
            [
              106.61293570660466,
              29.455696932218203
            ]
          ]
        ]
      },
      "properties" : {
        "FID" : 3,
        "SOURCE_ID" : 276,
        "Join_Count" : 2644,
        "GiZScore" : 12.5578271329,
        "GiPValue" : 0,
        "NNeighbors" : 5,
        "Gi_Bin" : 3
      }
    },
    {
      "type" : "Feature",
      "id" : 4,
      "geometry" : {
        "type" : "Polygon",
        "coordinates" : [
          [
            [
              106.11231118208302,
              29.774222680656258
            ],
            [
              106.11027581280935,
              29.882418477796186
            ],
            [
              105.98612547648847,
              29.880581584388082
            ],
            [
              105.98829435144542,
              29.772393768245745
            ],
            [
              106.11231118208302,
              29.774222680656258
            ]
          ]
        ]
      },
      "properties" : {
        "FID" : 4,
        "SOURCE_ID" : 280,
        "Join_Count" : 404,
        "GiZScore" : 1.69676777936,
        "GiPValue" : 0.089740572596599996,
        "NNeighbors" : 5,
        "Gi_Bin" : 1
      }
    },
    {
      "type" : "Feature",
      "id" : 5,
      "geometry" : {
        "type" : "Polygon",
        "coordinates" : [
          [
            [
              106.24011173481004,
              29.559523203037593
            ],
            [
              106.23823055154014,
              29.667730233217185
            ],
            [
              106.11433548760577,
              29.666024986090754
            ],
            [
              106.11634877910301,
              29.557825398821894
            ],
            [
              106.24011173481004,
              29.559523203037593
            ]
          ]
        ]
      },
      "properties" : {
        "FID" : 5,
        "SOURCE_ID" : 351,
        "Join_Count" : 419,
        "GiZScore" : 1.7695122164699999,
        "GiPValue" : 0.076808433899499998,
        "NNeighbors" : 5,
        "Gi_Bin" : 1
      }
    },
    {
      "type" : "Feature",
      "id" : 6,
      "geometry" : {
        "type" : "Polygon",
        "coordinates" : [
          [
            [
              106.61440416383546,
              29.347466943344674
            ],
            [
              106.61293570660466,
              29.455696932218203
            ],
            [
              106.48927568892397,
              29.45435083655935
            ],
            [
              106.49087494632576,
              29.346126750650011
            ],
            [
              106.61440416383546,
              29.347466943344674
            ]
          ]
        ]
      },
      "properties" : {
        "FID" : 6,
        "SOURCE_ID" : 447,
        "Join_Count" : 479,
        "GiZScore" : 2.0613483957400001,
        "GiPValue" : 0.039269814237400003,
        "NNeighbors" : 5,
        "Gi_Bin" : 2
      }
    },
    {
      "type" : "Feature",
      "id" : 7,
      "geometry" : {
        "type" : "Polygon",
        "coordinates" : [
          [
            [
              106.48442515409857,
              29.779012035094791
            ],
            [
              106.48279058947286,
              29.887228733354522
            ],
            [
              106.35860909817636,
              29.885742087364651
            ],
            [
              106.36037730900399,
              29.777531848964241
            ],
            [
              106.48442515409857,
              29.779012035094791
            ]
          ]
        ]
      },
      "properties" : {
        "FID" : 7,
        "SOURCE_ID" : 476,
        "Join_Count" : 685,
        "GiZScore" : 3.0590061848299999,
        "GiPValue" : 0.0022207256525600002,
        "NNeighbors" : 5,
        "Gi_Bin" : 3
      }
    },
    {
      "type" : "Feature",
      "id" : 8,
      "geometry" : {
        "type" : "Polygon",
        "coordinates" : [
          [
            [
              107.4776279234592,
              29.678412455451248
            ],
            [
              107.47706677002398,
              29.786664336527092
            ],
            [
              107.35296818872463,
              29.786115280793144
            ],
            [
              107.35366249043368,
              29.677865791268225
            ],
            [
              107.4776279234592,
              29.678412455451248
            ]
          ]
        ]
      },
      "properties" : {
        "FID" : 8,
        "SOURCE_ID" : 540,
        "Join_Count" : 539,
        "GiZScore" : 2.3512099821399999,
        "GiPValue" : 0.018712470574500002,
        "NNeighbors" : 5,
        "Gi_Bin" : 2
      }
    },
    {
      "type" : "Feature",
      "id" : 9,
      "geometry" : {
        "type" : "Polygon",
        "coordinates" : [
          [
            [
              106.4876676640245,
              29.562573082251937
            ],
            [
              106.48605083229683,
              29.670793483249202
            ],
            [
              106.36213590727803,
              29.66931974342576
            ],
            [
              106.36388493621453,
              29.561105775272473
            ],
            [
              106.4876676640245,
              29.562573082251937
            ]
          ]
        ]
      },
      "properties" : {
        "FID" : 9,
        "SOURCE_ID" : 544,
        "Join_Count" : 799,
        "GiZScore" : 3.6138667774600002,
        "GiPValue" : 0.00030166410706400002,
        "NNeighbors" : 5,
        "Gi_Bin" : 3
      }
    },
    {
      "type" : "Feature",
      "id" : 10,
      "geometry" : {
        "type" : "Polygon",
        "coordinates" : [
          [
            [
              105.99685249123893,
              29.339623410508359
            ],
            [
              105.99473045517676,
              29.447818854214354
            ],
            [
              105.87112143546834,
              29.445899130119116
            ],
            [
              105.87337404479715,
              29.337712103562808
            ],
            [
              105.99685249123893,
              29.339623410508359
            ]
          ]
        ]
      },
      "properties" : {
        "FID" : 10,
        "SOURCE_ID" : 559,
        "Join_Count" : 484,
        "GiZScore" : 2.0846003577299999,
        "GiPValue" : 0.0371055919998,
        "NNeighbors" : 5,
        "Gi_Bin" : 2
      }
    }
  ]
}